[{"sections": [{"minors": [], "sessionDates": null, "specialPermissionAddCode": null, "number": "01", "unitMajors": [], "subtitle": null, "specialPermissionDropCodeDescription": null, "specialPermissionAddCodeDescription": null, "subtopic": null, "majors": [{"code": "01", "isUnitCode": true, "isMajorCode": false}, {"code": "07", "isUnitCode": true, "isMajorCode": false}, {"code": "10", "isUnitCode": true, "isMajorCode": false}, {"code": "11", "isUnitCode": true, "isMajorCode": false}, {"code": "14", "isUnitCode": true, "isMajorCode": false}, {"code": "37", "isUnitCode": true, "isMajorCode": false}, {"code": "73", "isUnitCode": true, "isMajorCode": false}], "index": "18474", "sectionNotes": null, "specialPermissionDropCode": null, "comments": [{"code": "35", "description": "See online schedule for prereqs"}], "crossListedSections": [], "legendKey": null, "meetingTimes": [{"campusName": "LIVINGSTON", "startTime": "0500", "meetingDay": "T", "meetingModeDesc": "LEC", "roomNumber": "1095", "campusLocation": "3", "buildingCode": "BRR", "pmCode": "P", "baClassHours": null, "campusAbbrev": "LIV", "endTime": "0620", "meetingModeCode": "02"}, {"campusName": "LIVINGSTON", "startTime": "0500", "meetingDay": "TH", "meetingModeDesc": "LEC", "roomNumber": "1095", "campusLocation": "3", "buildingCode": "BRR", "pmCode": "P", "baClassHours": null, "campusAbbrev": "LIV", "endTime": "0620", "meetingModeCode": "02"}], "honorPrograms": [], "instructors": [{"name": "CITRO, C"}], "printed": "Y", "examCode": "C", "campusCode": "NB", "sectionEligibility": null, "sessionDatePrintIndicator": "Y", "openStatus": true}], "campusCode": "NB", "coreCodes": [], "courseNotes": null, "title": "INTRO TO FINANCE", "supplementCode": "  ", "subjectGroupNotes": null, "courseDescription": null, "synopsisUrl": null, "offeringUnitTitle": null, "openSections": 1, "credits": 3, "offeringUnitCode": "33", "preReqNotes": "((01:640:112  or 01:640:115 ) and (01:960:211 ))<em> OR </em> ((01:640:112  or 01:640:115 ) and (01:960:285 ))<em> OR </em> ((01:640:112  or 01:640:115 ) and (01:830:200 ))<em> OR </em> ((01:640:135  or 01:640:151 ) and (01:960:211 ))<em> OR </em> ((01:640:135  or 01:640:151 ) and (01:960:285 ))<em> OR </em> ((01:640:135  or 01:640:151 ) and (01:830:200 ))", "unitNotes": "School 33 courses that previously held the subject code of 623 can now be found under the subject number 136, under the title Business Analytics and Information Technology.", "subjectNotes": "NO SPECIAL PERMISSION WILL BE GRANTED FOR RUTGERS BUSINESS SCHOOL-UNDERGRADUATE NB COURSES.", "courseNumber": "203", "expandedTitle": "INTRODUCTION TO FINANCE                                                         ", "subject": "390"}, {"sections": [{"minors": [], "sessionDates": null, "specialPermissionAddCode": null, "number": "01", "unitMajors": [], "subtitle": null, "specialPermissionDropCodeDescription": null, "specialPermissionAddCodeDescription": null, "subtopic": null, "majors": [{"code": "799", "isUnitCode": false, "isMajorCode": true}, {"code": "630", "isUnitCode": false, "isMajorCode": true}, {"code": "136", "isUnitCode": false, "isMajorCode": true}, {"code": "010", "isUnitCode": false, "isMajorCode": true}, {"code": "620", "isUnitCode": false, "isMajorCode": true}], "index": "02568", "sectionNotes": "NO SP NUMBERS GIVEN FOR THISCOURSE; COURSE ASSOCIATED WITHRECITATIONS 33:390:301 SECTIONS3-5", "specialPermissionDropCode": null, "comments": [{"code": "19", "description": "School of Business Majors only"}], "crossListedSections": [], "legendKey": null, "meetingTimes": [{"campusName": "LIVINGSTON", "startTime": "1020", "meetingDay": "M", "meetingModeDesc": "LEC", "roomNumber": "1095", "campusLocation": "3", "buildingCode": "BRR", "pmCode": "A", "baClassHours": null, "campusAbbrev": "LIV", "endTime": "1140", "meetingModeCode": "02"}, {"campusName": "LIVINGSTON", "startTime": "1020", "meetingDay": "TH", "meetingModeDesc": "LEC", "roomNumber": "1095", "campusLocation": "3", "buildingCode": "BRR", "pmCode": "A", "baClassHours": null, "campusAbbrev": "LIV", "endTime": "1140", "meetingModeCode": "02"}], "honorPrograms": [], "instructors": [{"name": "NG, F"}], "printed": "Y", "examCode": "C", "campusCode": "NB", "sectionEligibility": "JUNIORS AND SENIORS ", "sessionDatePrintIndicator": "Y", "openStatus": true}], "campusCode": "NB", "coreCodes": [], "courseNotes": null, "title": "FINANCIAL MANAGEMENT", "supplementCode": "  ", "subjectGroupNotes": null, "courseDescription": null, "synopsisUrl": null, "offeringUnitTitle": null, "openSections": 1, "credits": 3, "offeringUnitCode": "33", "preReqNotes": "((01:640:135  or 01:640:151 ) and (01:960:211 ))<em> OR </em> ((01:640:135  or 01:640:151 ) and (01:960:285 ))", "unitNotes": "School 33 courses that previously held the subject code of 623 can now be found under the subject number 136, under the title Business Analytics and Information Technology.", "subjectNotes": "NO SPECIAL PERMISSION WILL BE GRANTED FOR RUTGERS BUSINESS SCHOOL-UNDERGRADUATE NB COURSES.", "courseNumber": "300", "expandedTitle": "FINANCIAL MANAGEMENT                                                            ", "subject": "390"}, {"sections": [{"minors": [], "sessionDates": null, "specialPermissionAddCode": null, "number": "02", "unitMajors": [], "subtitle": null, "specialPermissionDropCodeDescription": null, "specialPermissionAddCodeDescription": null, "subtopic": null, "majors": [{"code": "136", "isUnitCode": false, "isMajorCode": true}, {"code": "010", "isUnitCode": false, "isMajorCode": true}, {"code": "630", "isUnitCode": false, "isMajorCode": true}, {"code": "620", "isUnitCode": false, "isMajorCode": true}, {"code": "390", "isUnitCode": false, "isMajorCode": true}, {"code": "799", "isUnitCode": false, "isMajorCode": true}], "index": "12150", "sectionNotes": "ASSOCIATED WITH 33:390:310.01", "specialPermissionDropCode": null, "comments": [], "crossListedSections": [], "legendKey": null, "meetingTimes": [{"campusName": "LIVINGSTON", "startTime": "0515", "meetingDay": "M", "meetingModeDesc": "RECIT", "roomNumber": "5101", "campusLocation": "3", "buildingCode": "BRR", "pmCode": "P", "baClassHours": null, "campusAbbrev": "LIV", "endTime": "0610", "meetingModeCode": "03"}], "honorPrograms": [], "instructors": [], "printed": "Y", "examCode": "O", "campusCode": "NB", "sectionEligibility": "JUNIORS AND SENIORS ", "sessionDatePrintIndicator": "Y", "openStatus": true}, {"minors": [], "sessionDates": null, "specialPermissionAddCode": null, "number": "03", "unitMajors": [], "subtitle": null, "specialPermissionDropCodeDescription": null, "specialPermissionAddCodeDescription": null, "subtopic": null, "majors": [{"code": "010", "isUnitCode": false, "isMajorCode": true}, {"code": "799", "isUnitCode": false, "isMajorCode": true}, {"code": "630", "isUnitCode": false, "isMajorCode": true}, {"code": "136", "isUnitCode": false, "isMajorCode": true}, {"code": "390", "isUnitCode": false, "isMajorCode": true}, {"code": "620", "isUnitCode": false, "isMajorCode": true}], "index": "12151", "sectionNotes": "ASSOCIATED WITH 33:390:300:01", "specialPermissionDropCode": null, "comments": [], "crossListedSections": [], "legendKey": null, "meetingTimes": [{"campusName": "LIVINGSTON", "startTime": "1035", "meetingDay": "T", "meetingModeDesc": "RECIT", "roomNumber": "5073", "campusLocation": "3", "buildingCode": "BRR", "pmCode": "A", "baClassHours": null, "campusAbbrev": "LIV", "endTime": "1130", "meetingModeCode": "03"}], "honorPrograms": [], "instructors": [], "printed": "Y", "examCode": "O", "campusCode": "NB", "sectionEligibility": "JUNIORS AND SENIORS ", "sessionDatePrintIndicator": "Y", "openStatus": true}, {"minors": [], "sessionDates": null, "specialPermissionAddCode": null, "number": "04", "unitMajors": [], "subtitle": null, "specialPermissionDropCodeDescription": null, "specialPermissionAddCodeDescription": null, "subtopic": null, "majors": [{"code": "010", "isUnitCode": false, "isMajorCode": true}, {"code": "136", "isUnitCode": false, "isMajorCode": true}, {"code": "630", "isUnitCode": false, "isMajorCode": true}, {"code": "620", "isUnitCode": false, "isMajorCode": true}, {"code": "390", "isUnitCode": false, "isMajorCode": true}, {"code": "799", "isUnitCode": false, "isMajorCode": true}], "index": "12152", "sectionNotes": "ASSOCIATED WITH 33:390:300:01", "specialPermissionDropCode": null, "comments": [], "crossListedSections": [], "legendKey": null, "meetingTimes": [{"campusName": "LIVINGSTON", "startTime": "1215", "meetingDay": "T", "meetingModeDesc": "RECIT", "roomNumber": "5073", "campusLocation": "3", "buildingCode": "BRR", "pmCode": "P", "baClassHours": null, "campusAbbrev": "LIV", "endTime": "0110", "meetingModeCode": "03"}], "honorPrograms": [], "instructors": [], "printed": "Y", "examCode": "O", "campusCode": "NB", "sectionEligibility": "JUNIORS AND SENIORS ", "sessionDatePrintIndicator": "Y", "openStatus": true}, {"minors": [], "sessionDates": null, "specialPermissionAddCode": null, "number": "05", "unitMajors": [], "subtitle": null, "specialPermissionDropCodeDescription": null, "specialPermissionAddCodeDescription": null, "subtopic": null, "majors": [{"code": "390", "isUnitCode": false, "isMajorCode": true}, {"code": "010", "isUnitCode": false, "isMajorCode": true}, {"code": "136", "isUnitCode": false, "isMajorCode": true}, {"code": "620", "isUnitCode": false, "isMajorCode": true}, {"code": "630", "isUnitCode": false, "isMajorCode": true}, {"code": "799", "isUnitCode": false, "isMajorCode": true}], "index": "12153", "sectionNotes": "ASSOCIATED WITH 33:390:300:01", "specialPermissionDropCode": null, "comments": [], "crossListedSections": [], "legendKey": null, "meetingTimes": [{"campusName": "LIVINGSTON", "startTime": "0155", "meetingDay": "M", "meetingModeDesc": "RECIT", "roomNumber": "4087", "campusLocation": "3", "buildingCode": "BRR", "pmCode": "P", "baClassHours": null, "campusAbbrev": "LIV", "endTime": "0250", "meetingModeCode": "03"}], "honorPrograms": [], "instructors": [], "printed": "Y", "examCode": "O", "campusCode": "NB", "sectionEligibility": "JUNIORS AND SENIORS ", "sessionDatePrintIndicator": "Y", "openStatus": true}, {"minors": [], "sessionDates": null, "specialPermissionAddCode": null, "number": "07", "unitMajors": [], "subtitle": null, "specialPermissionDropCodeDescription": null, "specialPermissionAddCodeDescription": null, "subtopic": null, "majors": [{"code": "010", "isUnitCode": false, "isMajorCode": true}, {"code": "630", "isUnitCode": false, "isMajorCode": true}, {"code": "136", "isUnitCode": false, "isMajorCode": true}, {"code": "799", "isUnitCode": false, "isMajorCode": true}, {"code": "620", "isUnitCode": false, "isMajorCode": true}, {"code": "390", "isUnitCode": false, "isMajorCode": true}], "index": "12154", "sectionNotes": "ASSOCIATED WITH 33:390:310.01", "specialPermissionDropCode": null, "comments": [], "crossListedSections": [], "legendKey": null, "meetingTimes": [{"campusName": "LIVINGSTON", "startTime": "0515", "meetingDay": "W", "meetingModeDesc": "RECIT", "roomNumber": "5101", "campusLocation": "3", "buildingCode": "BRR", "pmCode": "P", "baClassHours": null, "campusAbbrev": "LIV", "endTime": "0610", "meetingModeCode": "03"}], "honorPrograms": [], "instructors": [], "printed": "Y", "examCode": "O", "campusCode": "NB", "sectionEligibility": "JUNIORS AND SENIORS ", "sessionDatePrintIndicator": "Y", "openStatus": true}, {"minors": [], "sessionDates": null, "specialPermissionAddCode": null, "number": "08", "unitMajors": [], "subtitle": null, "specialPermissionDropCodeDescription": null, "specialPermissionAddCodeDescription": null, "subtopic": null, "majors": [{"code": "799", "isUnitCode": false, "isMajorCode": true}, {"code": "630", "isUnitCode": false, "isMajorCode": true}, {"code": "620", "isUnitCode": false, "isMajorCode": true}, {"code": "390", "isUnitCode": false, "isMajorCode": true}, {"code": "136", "isUnitCode": false, "isMajorCode": true}, {"code": "010", "isUnitCode": false, "isMajorCode": true}], "index": "12155", "sectionNotes": "AFFILIATED WITH 33.390.300.01", "specialPermissionDropCode": null, "comments": [], "crossListedSections": [], "legendKey": null, "meetingTimes": [{"campusName": "LIVINGSTON", "startTime": "1215", "meetingDay": "F", "meetingModeDesc": "RECIT", "roomNumber": "5109", "campusLocation": "3", "buildingCode": "BRR", "pmCode": "P", "baClassHours": null, "campusAbbrev": "LIV", "endTime": "0110", "meetingModeCode": "03"}], "honorPrograms": [], "instructors": [], "printed": "Y", "examCode": "O", "campusCode": "NB", "sectionEligibility": "JUNIORS AND SENIORS ", "sessionDatePrintIndicator": "Y", "openStatus": true}, {"minors": [], "sessionDates": null, "specialPermissionAddCode": null, "number": "09", "unitMajors": [], "subtitle": null, "specialPermissionDropCodeDescription": null, "specialPermissionAddCodeDescription": null, "subtopic": null, "majors": [{"code": "136", "isUnitCode": false, "isMajorCode": true}, {"code": "390", "isUnitCode": false, "isMajorCode": true}, {"code": "620", "isUnitCode": false, "isMajorCode": true}, {"code": "630", "isUnitCode": false, "isMajorCode": true}, {"code": "799", "isUnitCode": false, "isMajorCode": true}, {"code": "010", "isUnitCode": false, "isMajorCode": true}], "index": "12157", "sectionNotes": "ASSOCIATED WITH 33:390:310SECTIONS 02, 04, AND H1", "specialPermissionDropCode": null, "comments": [], "crossListedSections": [], "legendKey": null, "meetingTimes": [{"campusName": "LIVINGSTON", "startTime": "0155", "meetingDay": "W", "meetingModeDesc": "RECIT", "roomNumber": "3031", "campusLocation": "3", "buildingCode": "BRR", "pmCode": "P", "baClassHours": null, "campusAbbrev": "LIV", "endTime": "0250", "meetingModeCode": "03"}], "honorPrograms": [], "instructors": [], "printed": "Y", "examCode": "O", "campusCode": "NB", "sectionEligibility": "JUNIORS AND SENIORS ", "sessionDatePrintIndicator": "Y", "openStatus": true}, {"minors": [], "sessionDates": null, "specialPermissionAddCode": null, "number": "10", "unitMajors": [], "subtitle": null, "specialPermissionDropCodeDescription": null, "specialPermissionAddCodeDescription": null, "subtopic": null, "majors": [{"code": "010", "isUnitCode": false, "isMajorCode": true}, {"code": "136", "isUnitCode": false, "isMajorCode": true}, {"code": "390", "isUnitCode": false, "isMajorCode": true}, {"code": "620", "isUnitCode": false, "isMajorCode": true}, {"code": "799", "isUnitCode": false, "isMajorCode": true}, {"code": "630", "isUnitCode": false, "isMajorCode": true}], "index": "12158", "sectionNotes": "AFFILIATED WITH 33.390.300.01", "specialPermissionDropCode": null, "comments": [], "crossListedSections": [], "legendKey": null, "meetingTimes": [{"campusName": "LIVINGSTON", "startTime": "0515", "meetingDay": "TH", "meetingModeDesc": "RECIT", "roomNumber": "5101", "campusLocation": "3", "buildingCode": "BRR", "pmCode": "P", "baClassHours": null, "campusAbbrev": "LIV", "endTime": "0610", "meetingModeCode": "03"}], "honorPrograms": [], "instructors": [], "printed": "Y", "examCode": "O", "campusCode": "NB", "sectionEligibility": "JUNIORS AND SENIORS ", "sessionDatePrintIndicator": "Y", "openStatus": true}, {"minors": [], "sessionDates": null, "specialPermissionAddCode": null, "number": "11", "unitMajors": [], "subtitle": null, "specialPermissionDropCodeDescription": null, "specialPermissionAddCodeDescription": null, "subtopic": null, "majors": [{"code": "136", "isUnitCode": false, "isMajorCode": true}, {"code": "390", "isUnitCode": false, "isMajorCode": true}, {"code": "620", "isUnitCode": false, "isMajorCode": true}, {"code": "630", "isUnitCode": false, "isMajorCode": true}, {"code": "799", "isUnitCode": false, "isMajorCode": true}, {"code": "010", "isUnitCode": false, "isMajorCode": true}], "index": "12159", "sectionNotes": "AFFILIATED WITH 33.390.310.01", "specialPermissionDropCode": null, "comments": [], "crossListedSections": [], "legendKey": null, "meetingTimes": [{"campusName": "LIVINGSTON", "startTime": "1035", "meetingDay": "F", "meetingModeDesc": "RECIT", "roomNumber": "5073", "campusLocation": "3", "buildingCode": "BRR", "pmCode": "A", "baClassHours": null, "campusAbbrev": "LIV", "endTime": "1130", "meetingModeCode": "03"}], "honorPrograms": [], "instructors": [], "printed": "Y", "examCode": "O", "campusCode": "NB", "sectionEligibility": "JUNIORS AND SENIORS ", "sessionDatePrintIndicator": "Y", "openStatus": true}, {"minors": [], "sessionDates": null, "specialPermissionAddCode": null, "number": "12", "unitMajors": [], "subtitle": null, "specialPermissionDropCodeDescription": null, "specialPermissionAddCodeDescription": null, "subtopic": null, "majors": [{"code": "136", "isUnitCode": false, "isMajorCode": true}, {"code": "390", "isUnitCode": false, "isMajorCode": true}, {"code": "620", "isUnitCode": false, "isMajorCode": true}, {"code": "630", "isUnitCode": false, "isMajorCode": true}, {"code": "799", "isUnitCode": false, "isMajorCode": true}, {"code": "010", "isUnitCode": false, "isMajorCode": true}], "index": "12160", "sectionNotes": "ASSOCIATED WITH 33:390:310", "specialPermissionDropCode": null, "comments": [], "crossListedSections": [], "legendKey": null, "meetingTimes": [{"campusName": "LIVINGSTON", "startTime": "1215", "meetingDay": "F", "meetingModeDesc": "RECIT", "roomNumber": "5073", "campusLocation": "3", "buildingCode": "BRR", "pmCode": "P", "baClassHours": null, "campusAbbrev": "LIV", "endTime": "0110", "meetingModeCode": "03"}], "honorPrograms": [], "instructors": [], "printed": "N", "examCode": "O", "campusCode": "NB", "sectionEligibility": "JUNIORS AND SENIORS ", "sessionDatePrintIndicator": "Y", "openStatus": false}], "campusCode": "NB", "coreCodes": [], "courseNotes": null, "title": "CLASS ASSIST FIN MGT", "supplementCode": "  ", "subjectGroupNotes": null, "courseDescription": null, "synopsisUrl": null, "offeringUnitTitle": null, "openSections": 9, "credits": 0, "offeringUnitCode": "33", "preReqNotes": null, "unitNotes": "School 33 courses that previously held the subject code of 623 can now be found under the subject number 136, under the title Business Analytics and Information Technology.", "subjectNotes": "NO SPECIAL PERMISSION WILL BE GRANTED FOR RUTGERS BUSINESS SCHOOL-UNDERGRADUATE NB COURSES.", "courseNumber": "301", "expandedTitle": "CLASSROOM ASSISTANCE IN FINANCIAL MANAGEMENT                                    ", "subject": "390"}, {"sections": [{"minors": [], "sessionDates": null, "specialPermissionAddCode": null, "number": "01", "unitMajors": [], "subtitle": null, "specialPermissionDropCodeDescription": null, "specialPermissionAddCodeDescription": null, "subtopic": null, "majors": [{"code": "799", "isUnitCode": false, "isMajorCode": true}, {"code": "630", "isUnitCode": false, "isMajorCode": true}, {"code": "010", "isUnitCode": false, "isMajorCode": true}, {"code": "136", "isUnitCode": false, "isMajorCode": true}, {"code": "390", "isUnitCode": false, "isMajorCode": true}, {"code": "620", "isUnitCode": false, "isMajorCode": true}], "index": "12081", "sectionNotes": "RECOMMENDED RECITATIONS FOR THISCOURSE: 33:390:301 SECTIONS2,7, 11", "specialPermissionDropCode": null, "comments": [{"code": "35", "description": "See online schedule for prereqs"}], "crossListedSections": [], "legendKey": null, "meetingTimes": [{"campusName": "LIVINGSTON", "startTime": "0140", "meetingDay": "TH", "meetingModeDesc": "LEC", "roomNumber": "1071", "campusLocation": "3", "buildingCode": "BRR", "pmCode": "P", "baClassHours": null, "campusAbbrev": "LIV", "endTime": "0300", "meetingModeCode": "02"}, {"campusName": "LIVINGSTON", "startTime": "0140", "meetingDay": "T", "meetingModeDesc": "LEC", "roomNumber": "1071", "campusLocation": "3", "buildingCode": "BRR", "pmCode": "P", "baClassHours": null, "campusAbbrev": "LIV", "endTime": "0300", "meetingModeCode": "02"}], "honorPrograms": [], "instructors": [{"name": "PALMON, O"}], "printed": "Y", "examCode": "C", "campusCode": "NB", "sectionEligibility": "JUNIORS AND SENIORS ", "sessionDatePrintIndicator": "Y", "openStatus": true}, {"minors": [], "sessionDates": null, "specialPermissionAddCode": null, "number": "02", "unitMajors": [], "subtitle": null, "specialPermissionDropCodeDescription": null, "specialPermissionAddCodeDescription": null, "subtopic": null, "majors": [{"code": "799", "isUnitCode": false, "isMajorCode": true}, {"code": "136", "isUnitCode": false, "isMajorCode": true}, {"code": "390", "isUnitCode": false, "isMajorCode": true}, {"code": "620", "isUnitCode": false, "isMajorCode": true}, {"code": "630", "isUnitCode": false, "isMajorCode": true}, {"code": "010", "isUnitCode": false, "isMajorCode": true}], "index": "12175", "sectionNotes": "RECOMMENDED RECITATIONS FOR THISCOURSE 33:390:301 SECTION9", "specialPermissionDropCode": null, "comments": [], "crossListedSections": [], "legendKey": null, "meetingTimes": [{"campusName": "LIVINGSTON", "startTime": "0320", "meetingDay": "TH", "meetingModeDesc": "LEC", "roomNumber": "3085", "campusLocation": "3", "buildingCode": "BRR", "pmCode": "P", "baClassHours": null, "campusAbbrev": "LIV", "endTime": "0440", "meetingModeCode": "02"}, {"campusName": "LIVINGSTON", "startTime": "0320", "meetingDay": "T", "meetingModeDesc": "LEC", "roomNumber": "3085", "campusLocation": "3", "buildingCode": "BRR", "pmCode": "P", "baClassHours": null, "campusAbbrev": "LIV", "endTime": "0440", "meetingModeCode": "02"}], "honorPrograms": [], "instructors": [{"name": "PALMON, O"}], "printed": "Y", "examCode": "C", "campusCode": "NB", "sectionEligibility": "JUNIORS AND SENIORS ", "sessionDatePrintIndicator": "Y", "openStatus": false}, {"minors": [], "sessionDates": null, "specialPermissionAddCode": null, "number": "04", "unitMajors": [], "subtitle": null, "specialPermissionDropCodeDescription": null, "specialPermissionAddCodeDescription": null, "subtopic": null, "majors": [{"code": "799", "isUnitCode": false, "isMajorCode": true}, {"code": "630", "isUnitCode": false, "isMajorCode": true}, {"code": "620", "isUnitCode": false, "isMajorCode": true}, {"code": "390", "isUnitCode": false, "isMajorCode": true}, {"code": "136", "isUnitCode": false, "isMajorCode": true}, {"code": "010", "isUnitCode": false, "isMajorCode": true}], "index": "17160", "sectionNotes": "RECOMMENDED RECITATIONS FOR THISCOURSE ARE 33.390.301 SECTION9", "specialPermissionDropCode": null, "comments": [{"code": "35", "description": "See online schedule for prereqs"}], "crossListedSections": [], "legendKey": null, "meetingTimes": [{"campusName": "LIVINGSTON", "startTime": "0140", "meetingDay": "T", "meetingModeDesc": "LEC", "roomNumber": "2071", "campusLocation": "3", "buildingCode": "BRR", "pmCode": "P", "baClassHours": null, "campusAbbrev": "LIV", "endTime": "0300", "meetingModeCode": "02"}, {"campusName": "LIVINGSTON", "startTime": "0140", "meetingDay": "TH", "meetingModeDesc": "LEC", "roomNumber": "2071", "campusLocation": "3", "buildingCode": "BRR", "pmCode": "P", "baClassHours": null, "campusAbbrev": "LIV", "endTime": "0300", "meetingModeCode": "02"}], "honorPrograms": [], "instructors": [{"name": "CITRO, C"}], "printed": "Y", "examCode": "C", "campusCode": "NB", "sectionEligibility": "JUNIORS AND SENIORS ", "sessionDatePrintIndicator": "Y", "openStatus": true}, {"minors": [], "sessionDates": null, "specialPermissionAddCode": null, "number": "H1", "unitMajors": [], "subtitle": null, "specialPermissionDropCodeDescription": null, "specialPermissionAddCodeDescription": null, "subtopic": null, "majors": [{"code": "620", "isUnitCode": false, "isMajorCode": true}, {"code": "390", "isUnitCode": false, "isMajorCode": true}, {"code": "630", "isUnitCode": false, "isMajorCode": true}, {"code": "010", "isUnitCode": false, "isMajorCode": true}, {"code": "799", "isUnitCode": false, "isMajorCode": true}, {"code": "136", "isUnitCode": false, "isMajorCode": true}], "index": "12176", "sectionNotes": "RECOMMENDED RECITATIONS FOR THISCOURSE 33:390:301 SECTION 9", "specialPermissionDropCode": null, "comments": [{"code": "87", "description": "For Honors Students only"}], "crossListedSections": [], "legendKey": null, "meetingTimes": [{"campusName": "LIVINGSTON", "startTime": "0320", "meetingDay": "T", "meetingModeDesc": "LEC", "roomNumber": "3085", "campusLocation": "3", "buildingCode": "BRR", "pmCode": "P", "baClassHours": null, "campusAbbrev": "LIV", "endTime": "0440", "meetingModeCode": "02"}, {"campusName": "LIVINGSTON", "startTime": "0320", "meetingDay": "TH", "meetingModeDesc": "LEC", "roomNumber": "3085", "campusLocation": "3", "buildingCode": "BRR", "pmCode": "P", "baClassHours": null, "campusAbbrev": "LIV", "endTime": "0440", "meetingModeCode": "02"}], "honorPrograms": [{"code": "A"}], "instructors": [{"name": "PALMON, O"}], "printed": "Y", "examCode": "C", "campusCode": "NB", "sectionEligibility": "JUNIORS AND SENIORS ", "sessionDatePrintIndicator": "Y", "openStatus": true}], "campusCode": "NB", "coreCodes": [], "courseNotes": null, "title": "FIN MGT FOR FIN MAJS", "supplementCode": "  ", "subjectGroupNotes": null, "courseDescription": null, "synopsisUrl": null, "offeringUnitTitle": null, "openSections": 3, "credits": 3, "offeringUnitCode": "33", "preReqNotes": "((01:640:135  or 01:640:151 ) and (01:960:211 ))<em> OR </em> ((01:640:135  or 01:640:151 ) and (01:960:285 ))", "unitNotes": "School 33 courses that previously held the subject code of 623 can now be found under the subject number 136, under the title Business Analytics and Information Technology.", "subjectNotes": "NO SPECIAL PERMISSION WILL BE GRANTED FOR RUTGERS BUSINESS SCHOOL-UNDERGRADUATE NB COURSES.", "courseNumber": "310", "expandedTitle": "FINANCIAL MANAGEMENT FOR FINANCE MAJORS                                         ", "subject": "390"}, {"sections": [{"minors": [], "sessionDates": null, "specialPermissionAddCode": null, "number": "01", "unitMajors": [], "subtitle": null, "specialPermissionDropCodeDescription": null, "specialPermissionAddCodeDescription": null, "subtopic": null, "majors": [{"code": "390", "isUnitCode": false, "isMajorCode": true}], "index": "06302", "sectionNotes": "FINANCE MAJS ONLY; NO SPNUMBERS GIVEN FOR THIS COURSE", "specialPermissionDropCode": null, "comments": [{"code": "35", "description": "See online schedule for prereqs"}], "crossListedSections": [], "legendKey": null, "meetingTimes": [{"campusName": "LIVINGSTON", "startTime": "1020", "meetingDay": "W", "meetingModeDesc": "LEC", "roomNumber": "3085", "campusLocation": "3", "buildingCode": "BRR", "pmCode": "A", "baClassHours": null, "campusAbbrev": "LIV", "endTime": "0120", "meetingModeCode": "02"}], "honorPrograms": [], "instructors": [{"name": "WEAVER, D"}], "printed": "Y", "examCode": "C", "campusCode": "NB", "sectionEligibility": "JUNIORS AND SENIORS ", "sessionDatePrintIndicator": "Y", "openStatus": false}, {"minors": [], "sessionDates": null, "specialPermissionAddCode": null, "number": "03", "unitMajors": [], "subtitle": null, "specialPermissionDropCodeDescription": null, "specialPermissionAddCodeDescription": null, "subtopic": null, "majors": [{"code": "390", "isUnitCode": false, "isMajorCode": true}], "index": "02048", "sectionNotes": "FINANCE MAJS ONLY; NO SPNUMBERS GIVEN FOR THIS COURSE", "specialPermissionDropCode": null, "comments": [{"code": "35", "description": "See online schedule for prereqs"}], "crossListedSections": [], "legendKey": null, "meetingTimes": [{"campusName": "LIVINGSTON", "startTime": "0640", "meetingDay": "W", "meetingModeDesc": "LEC", "roomNumber": "1071", "campusLocation": "3", "buildingCode": "BRR", "pmCode": "P", "baClassHours": null, "campusAbbrev": "LIV", "endTime": "0930", "meetingModeCode": "02"}], "honorPrograms": [], "instructors": [{"name": "WEAVER, D"}], "printed": "Y", "examCode": "S", "campusCode": "NB", "sectionEligibility": "JUNIORS AND SENIORS ", "sessionDatePrintIndicator": "Y", "openStatus": false}], "campusCode": "NB", "coreCodes": [], "courseNotes": null, "title": "GLOBAL CAPITAL MKTS", "supplementCode": "  ", "subjectGroupNotes": null, "courseDescription": null, "synopsisUrl": null, "offeringUnitTitle": null, "openSections": 0, "credits": 3, "offeringUnitCode": "33", "preReqNotes": "(33:390:300 )<em> OR </em>(33:390:310 )", "unitNotes": "School 33 courses that previously held the subject code of 623 can now be found under the subject number 136, under the title Business Analytics and Information Technology.", "subjectNotes": "NO SPECIAL PERMISSION WILL BE GRANTED FOR RUTGERS BUSINESS SCHOOL-UNDERGRADUATE NB COURSES.", "courseNumber": "320", "expandedTitle": "GLOBAL CAPITAL MARKETS                                                          ", "subject": "390"}, {"sections": [{"minors": [], "sessionDates": null, "specialPermissionAddCode": null, "number": "01", "unitMajors": [], "subtitle": null, "specialPermissionDropCodeDescription": null, "specialPermissionAddCodeDescription": null, "subtopic": null, "majors": [{"code": "390", "isUnitCode": false, "isMajorCode": true}], "index": "07492", "sectionNotes": null, "specialPermissionDropCode": null, "comments": [{"code": "35", "description": "See online schedule for prereqs"}], "crossListedSections": [], "legendKey": null, "meetingTimes": [{"campusName": "LIVINGSTON", "startTime": "1020", "meetingDay": "M", "meetingModeDesc": "LEC", "roomNumber": "5073", "campusLocation": "3", "buildingCode": "BRR", "pmCode": "A", "baClassHours": null, "campusAbbrev": "LIV", "endTime": "1140", "meetingModeCode": "02"}, {"campusName": "LIVINGSTON", "startTime": "1020", "meetingDay": "TH", "meetingModeDesc": "LEC", "roomNumber": "5073", "campusLocation": "3", "buildingCode": "BRR", "pmCode": "A", "baClassHours": null, "campusAbbrev": "LIV", "endTime": "1140", "meetingModeCode": "02"}], "honorPrograms": [], "instructors": [{"name": "WINDER, J"}], "printed": "Y", "examCode": "C", "campusCode": "NB", "sectionEligibility": "JUNIORS AND SENIORS ", "sessionDatePrintIndicator": "Y", "openStatus": false}, {"minors": [], "sessionDates": null, "specialPermissionAddCode": null, "number": "02", "unitMajors": [], "subtitle": null, "specialPermissionDropCodeDescription": null, "specialPermissionAddCodeDescription": null, "subtopic": null, "majors": [{"code": "390", "isUnitCode": false, "isMajorCode": true}], "index": "09264", "sectionNotes": null, "specialPermissionDropCode": null, "comments": [], "crossListedSections": [], "legendKey": null, "meetingTimes": [{"campusName": "LIVINGSTON", "startTime": "1200", "meetingDay": "M", "meetingModeDesc": "LEC", "roomNumber": "5073", "campusLocation": "3", "buildingCode": "BRR", "pmCode": "P", "baClassHours": null, "campusAbbrev": "LIV", "endTime": "0120", "meetingModeCode": "02"}, {"campusName": "LIVINGSTON", "startTime": "1200", "meetingDay": "TH", "meetingModeDesc": "LEC", "roomNumber": "5073", "campusLocation": "3", "buildingCode": "BRR", "pmCode": "P", "baClassHours": null, "campusAbbrev": "LIV", "endTime": "0120", "meetingModeCode": "02"}], "honorPrograms": [], "instructors": [{"name": "WINDER, J"}], "printed": "Y", "examCode": "C", "campusCode": "NB", "sectionEligibility": "JUNIORS AND SENIORS ", "sessionDatePrintIndicator": "Y", "openStatus": false}, {"minors": [], "sessionDates": null, "specialPermissionAddCode": null, "number": "03", "unitMajors": [], "subtitle": null, "specialPermissionDropCodeDescription": null, "specialPermissionAddCodeDescription": null, "subtopic": null, "majors": [{"code": "390", "isUnitCode": false, "isMajorCode": true}], "index": "11851", "sectionNotes": null, "specialPermissionDropCode": null, "comments": [], "crossListedSections": [], "legendKey": null, "meetingTimes": [{"campusName": "LIVINGSTON", "startTime": "0320", "meetingDay": "M", "meetingModeDesc": "LEC", "roomNumber": "4085", "campusLocation": "3", "buildingCode": "BRR", "pmCode": "P", "baClassHours": null, "campusAbbrev": "LIV", "endTime": "0440", "meetingModeCode": "02"}, {"campusName": "LIVINGSTON", "startTime": "0320", "meetingDay": "W", "meetingModeDesc": "LEC", "roomNumber": "4085", "campusLocation": "3", "buildingCode": "BRR", "pmCode": "P", "baClassHours": null, "campusAbbrev": "LIV", "endTime": "0440", "meetingModeCode": "02"}], "honorPrograms": [], "instructors": [{"name": "WINDER, J"}], "printed": "Y", "examCode": "C", "campusCode": "NB", "sectionEligibility": "JUNIORS AND SENIORS ", "sessionDatePrintIndicator": "Y", "openStatus": false}], "campusCode": "NB", "coreCodes": [], "courseNotes": null, "title": "GLOB MON MKTS & INST", "supplementCode": "  ", "subjectGroupNotes": null, "courseDescription": null, "synopsisUrl": null, "offeringUnitTitle": null, "openSections": 0, "credits": 3, "offeringUnitCode": "33", "preReqNotes": "(33:390:300 )<em> OR </em>(33:390:310 )", "unitNotes": "School 33 courses that previously held the subject code of 623 can now be found under the subject number 136, under the title Business Analytics and Information Technology.", "subjectNotes": "NO SPECIAL PERMISSION WILL BE GRANTED FOR RUTGERS BUSINESS SCHOOL-UNDERGRADUATE NB COURSES.", "courseNumber": "375", "expandedTitle": "GLOBAL MONEY MARKETS AND INSTITUTIONS                                           ", "subject": "390"}, {"sections": [{"minors": [], "sessionDates": null, "specialPermissionAddCode": null, "number": "01", "unitMajors": [], "subtitle": null, "specialPermissionDropCodeDescription": null, "specialPermissionAddCodeDescription": null, "subtopic": null, "majors": [{"code": "390", "isUnitCode": false, "isMajorCode": true}], "index": "08303", "sectionNotes": null, "specialPermissionDropCode": null, "comments": [{"code": "35", "description": "See online schedule for prereqs"}], "crossListedSections": [], "legendKey": null, "meetingTimes": [{"campusName": "LIVINGSTON", "startTime": "0140", "meetingDay": "W", "meetingModeDesc": "LEC", "roomNumber": "4073", "campusLocation": "3", "buildingCode": "BRR", "pmCode": "P", "baClassHours": null, "campusAbbrev": "LIV", "endTime": "0300", "meetingModeCode": "02"}, {"campusName": "LIVINGSTON", "startTime": "0140", "meetingDay": "M", "meetingModeDesc": "LEC", "roomNumber": "4073", "campusLocation": "3", "buildingCode": "BRR", "pmCode": "P", "baClassHours": null, "campusAbbrev": "LIV", "endTime": "0300", "meetingModeCode": "02"}], "honorPrograms": [], "instructors": [{"name": "AMATI, A"}], "printed": "Y", "examCode": "C", "campusCode": "NB", "sectionEligibility": "JUNIORS AND SENIORS ", "sessionDatePrintIndicator": "Y", "openStatus": false}, {"minors": [], "sessionDates": null, "specialPermissionAddCode": null, "number": "02", "unitMajors": [], "subtitle": null, "specialPermissionDropCodeDescription": null, "specialPermissionAddCodeDescription": null, "subtopic": null, "majors": [{"code": "390", "isUnitCode": false, "isMajorCode": true}], "index": "10471", "sectionNotes": null, "specialPermissionDropCode": null, "comments": [], "crossListedSections": [], "legendKey": null, "meetingTimes": [{"campusName": "LIVINGSTON", "startTime": "1020", "meetingDay": "M", "meetingModeDesc": "LEC", "roomNumber": "5105", "campusLocation": "3", "buildingCode": "BRR", "pmCode": "A", "baClassHours": null, "campusAbbrev": "LIV", "endTime": "1140", "meetingModeCode": "02"}, {"campusName": "LIVINGSTON", "startTime": "1020", "meetingDay": "TH", "meetingModeDesc": "LEC", "roomNumber": "5105", "campusLocation": "3", "buildingCode": "BRR", "pmCode": "A", "baClassHours": null, "campusAbbrev": "LIV", "endTime": "1140", "meetingModeCode": "02"}], "honorPrograms": [], "instructors": [{"name": "PAREEK, A"}], "printed": "Y", "examCode": "C", "campusCode": "NB", "sectionEligibility": "JUNIORS AND SENIORS ", "sessionDatePrintIndicator": "Y", "openStatus": false}, {"minors": [], "sessionDates": null, "specialPermissionAddCode": null, "number": "03", "unitMajors": [], "subtitle": null, "specialPermissionDropCodeDescription": null, "specialPermissionAddCodeDescription": null, "subtopic": null, "majors": [{"code": "390", "isUnitCode": false, "isMajorCode": true}], "index": "08288", "sectionNotes": null, "specialPermissionDropCode": null, "comments": [{"code": "35", "description": "See online schedule for prereqs"}], "crossListedSections": [], "legendKey": null, "meetingTimes": [{"campusName": "LIVINGSTON", "startTime": "1200", "meetingDay": "M", "meetingModeDesc": "LEC", "roomNumber": "5105", "campusLocation": "3", "buildingCode": "BRR", "pmCode": "P", "baClassHours": null, "campusAbbrev": "LIV", "endTime": "0120", "meetingModeCode": "02"}, {"campusName": "LIVINGSTON", "startTime": "1200", "meetingDay": "TH", "meetingModeDesc": "LEC", "roomNumber": "5105", "campusLocation": "3", "buildingCode": "BRR", "pmCode": "P", "baClassHours": null, "campusAbbrev": "LIV", "endTime": "0120", "meetingModeCode": "02"}], "honorPrograms": [], "instructors": [{"name": "PAREEK, A"}], "printed": "Y", "examCode": "C", "campusCode": "NB", "sectionEligibility": "JUNIORS AND SENIORS ", "sessionDatePrintIndicator": "Y", "openStatus": false}, {"minors": [], "sessionDates": null, "specialPermissionAddCode": null, "number": "04", "unitMajors": [], "subtitle": null, "specialPermissionDropCodeDescription": null, "specialPermissionAddCodeDescription": null, "subtopic": null, "majors": [{"code": "390", "isUnitCode": false, "isMajorCode": true}], "index": "16949", "sectionNotes": null, "specialPermissionDropCode": null, "comments": [{"code": "35", "description": "See online schedule for prereqs"}], "crossListedSections": [], "legendKey": null, "meetingTimes": [{"campusName": "LIVINGSTON", "startTime": "0640", "meetingDay": "M", "meetingModeDesc": "LEC", "roomNumber": "4073", "campusLocation": "3", "buildingCode": "BRR", "pmCode": "P", "baClassHours": null, "campusAbbrev": "LIV", "endTime": "0930", "meetingModeCode": "02"}], "honorPrograms": [], "instructors": [{"name": "NG, F"}], "printed": "Y", "examCode": "S", "campusCode": "NB", "sectionEligibility": "JUNIORS AND SENIORS ", "sessionDatePrintIndicator": "Y", "openStatus": false}], "campusCode": "NB", "coreCodes": [], "courseNotes": null, "title": "INVSTMNT ANALYSIS", "supplementCode": "  ", "subjectGroupNotes": null, "courseDescription": null, "synopsisUrl": null, "offeringUnitTitle": null, "openSections": 0, "credits": 3, "offeringUnitCode": "33", "preReqNotes": "(33:390:300 )<em> OR </em>(33:390:310 )", "unitNotes": "School 33 courses that previously held the subject code of 623 can now be found under the subject number 136, under the title Business Analytics and Information Technology.", "subjectNotes": "NO SPECIAL PERMISSION WILL BE GRANTED FOR RUTGERS BUSINESS SCHOOL-UNDERGRADUATE NB COURSES.", "courseNumber": "380", "expandedTitle": null, "subject": "390"}, {"sections": [{"minors": [], "sessionDates": null, "specialPermissionAddCode": null, "number": "01", "unitMajors": [], "subtitle": null, "specialPermissionDropCodeDescription": null, "specialPermissionAddCodeDescription": null, "subtopic": null, "majors": [{"code": "390", "isUnitCode": false, "isMajorCode": true}], "index": "10479", "sectionNotes": null, "specialPermissionDropCode": null, "comments": [{"code": "35", "description": "See online schedule for prereqs"}], "crossListedSections": [], "legendKey": null, "meetingTimes": [{"campusName": "LIVINGSTON", "startTime": "1020", "meetingDay": "W", "meetingModeDesc": "LEC", "roomNumber": "5095", "campusLocation": "3", "buildingCode": "BRR", "pmCode": "A", "baClassHours": null, "campusAbbrev": "LIV", "endTime": "0120", "meetingModeCode": "02"}], "honorPrograms": [], "instructors": [{"name": "LONGO, J"}], "printed": "Y", "examCode": "C", "campusCode": "NB", "sectionEligibility": "JUNIORS AND SENIORS ", "sessionDatePrintIndicator": "Y", "openStatus": false}], "campusCode": "NB", "coreCodes": [], "courseNotes": null, "title": "INVEST BANK ANALYSIS", "supplementCode": "  ", "subjectGroupNotes": null, "courseDescription": null, "synopsisUrl": null, "offeringUnitTitle": null, "openSections": 0, "credits": 3, "offeringUnitCode": "33", "preReqNotes": "(33:390:400 )", "unitNotes": "School 33 courses that previously held the subject code of 623 can now be found under the subject number 136, under the title Business Analytics and Information Technology.", "subjectNotes": "NO SPECIAL PERMISSION WILL BE GRANTED FOR RUTGERS BUSINESS SCHOOL-UNDERGRADUATE NB COURSES.", "courseNumber": "385", "expandedTitle": "INVESTMENT BANKING ANALYSIS                                                     ", "subject": "390"}, {"sections": [{"minors": [], "sessionDates": null, "specialPermissionAddCode": null, "number": "01", "unitMajors": [], "subtitle": null, "specialPermissionDropCodeDescription": null, "specialPermissionAddCodeDescription": null, "subtopic": null, "majors": [{"code": "390", "isUnitCode": false, "isMajorCode": true}], "index": "08304", "sectionNotes": null, "specialPermissionDropCode": null, "comments": [{"code": "35", "description": "See online schedule for prereqs"}], "crossListedSections": [], "legendKey": null, "meetingTimes": [{"campusName": "LIVINGSTON", "startTime": "0140", "meetingDay": "T", "meetingModeDesc": "LEC", "roomNumber": "5073", "campusLocation": "3", "buildingCode": "BRR", "pmCode": "P", "baClassHours": null, "campusAbbrev": "LIV", "endTime": "0300", "meetingModeCode": "02"}, {"campusName": "LIVINGSTON", "startTime": "0140", "meetingDay": "TH", "meetingModeDesc": "LEC", "roomNumber": "5073", "campusLocation": "3", "buildingCode": "BRR", "pmCode": "P", "baClassHours": null, "campusAbbrev": "LIV", "endTime": "0300", "meetingModeCode": "02"}], "honorPrograms": [], "instructors": [{"name": "KEDIA, S"}], "printed": "Y", "examCode": "C", "campusCode": "NB", "sectionEligibility": "JUNIORS AND SENIORS ", "sessionDatePrintIndicator": "Y", "openStatus": false}, {"minors": [], "sessionDates": null, "specialPermissionAddCode": null, "number": "02", "unitMajors": [], "subtitle": null, "specialPermissionDropCodeDescription": null, "specialPermissionAddCodeDescription": null, "subtopic": null, "majors": [{"code": "390", "isUnitCode": false, "isMajorCode": true}], "index": "10480", "sectionNotes": null, "specialPermissionDropCode": null, "comments": [], "crossListedSections": [], "legendKey": null, "meetingTimes": [{"campusName": "LIVINGSTON", "startTime": "0320", "meetingDay": "T", "meetingModeDesc": "LEC", "roomNumber": "5073", "campusLocation": "3", "buildingCode": "BRR", "pmCode": "P", "baClassHours": null, "campusAbbrev": "LIV", "endTime": "0440", "meetingModeCode": "02"}, {"campusName": "LIVINGSTON", "startTime": "0320", "meetingDay": "TH", "meetingModeDesc": "LEC", "roomNumber": "5073", "campusLocation": "3", "buildingCode": "BRR", "pmCode": "P", "baClassHours": null, "campusAbbrev": "LIV", "endTime": "0440", "meetingModeCode": "02"}], "honorPrograms": [], "instructors": [{"name": "KEDIA, S"}], "printed": "Y", "examCode": "C", "campusCode": "NB", "sectionEligibility": "JUNIORS AND SENIORS ", "sessionDatePrintIndicator": "Y", "openStatus": false}, {"minors": [], "sessionDates": null, "specialPermissionAddCode": null, "number": "04", "unitMajors": [], "subtitle": null, "specialPermissionDropCodeDescription": null, "specialPermissionAddCodeDescription": null, "subtopic": null, "majors": [{"code": "390", "isUnitCode": false, "isMajorCode": true}], "index": "08305", "sectionNotes": null, "specialPermissionDropCode": null, "comments": [], "crossListedSections": [], "legendKey": null, "meetingTimes": [{"campusName": "LIVINGSTON", "startTime": "0640", "meetingDay": "T", "meetingModeDesc": "LEC", "roomNumber": "5101", "campusLocation": "3", "buildingCode": "BRR", "pmCode": "P", "baClassHours": null, "campusAbbrev": "LIV", "endTime": "0930", "meetingModeCode": "02"}], "honorPrograms": [], "instructors": [{"name": "HASSAN, M"}], "printed": "Y", "examCode": "S", "campusCode": "NB", "sectionEligibility": "JUNIORS AND SENIORS ", "sessionDatePrintIndicator": "Y", "openStatus": true}, {"minors": [], "sessionDates": null, "specialPermissionAddCode": null, "number": "05", "unitMajors": [], "subtitle": null, "specialPermissionDropCodeDescription": null, "specialPermissionAddCodeDescription": null, "subtopic": null, "majors": [{"code": "390", "isUnitCode": false, "isMajorCode": true}], "index": "16943", "sectionNotes": null, "specialPermissionDropCode": null, "comments": [], "crossListedSections": [], "legendKey": null, "meetingTimes": [{"campusName": "LIVINGSTON", "startTime": "1020", "meetingDay": "W", "meetingModeDesc": "LEC", "roomNumber": "3071", "campusLocation": "3", "buildingCode": "BRR", "pmCode": "A", "baClassHours": null, "campusAbbrev": "LIV", "endTime": "0120", "meetingModeCode": "02"}], "honorPrograms": [], "instructors": [{"name": "KIM, J M"}], "printed": "Y", "examCode": "C", "campusCode": "NB", "sectionEligibility": "JUNIORS AND SENIORS ", "sessionDatePrintIndicator": "Y", "openStatus": true}], "campusCode": "NB", "coreCodes": [], "courseNotes": null, "title": "CORPORATE FINANCE", "supplementCode": "  ", "subjectGroupNotes": null, "courseDescription": null, "synopsisUrl": null, "offeringUnitTitle": null, "openSections": 2, "credits": 3, "offeringUnitCode": "33", "preReqNotes": "(33:390:300 )<em> OR </em>(33:390:310 )", "unitNotes": "School 33 courses that previously held the subject code of 623 can now be found under the subject number 136, under the title Business Analytics and Information Technology.", "subjectNotes": "NO SPECIAL PERMISSION WILL BE GRANTED FOR RUTGERS BUSINESS SCHOOL-UNDERGRADUATE NB COURSES.", "courseNumber": "400", "expandedTitle": null, "subject": "390"}, {"sections": [{"minors": [], "sessionDates": null, "specialPermissionAddCode": null, "number": "01", "unitMajors": [], "subtitle": null, "specialPermissionDropCodeDescription": null, "specialPermissionAddCodeDescription": null, "subtopic": null, "majors": [{"code": "390", "isUnitCode": false, "isMajorCode": true}], "index": "05734", "sectionNotes": "FINANCE MAJS ONLY; NO SPNUMBERS GIVEN FOR THIS COURSE", "specialPermissionDropCode": null, "comments": [{"code": "35", "description": "See online schedule for prereqs"}], "crossListedSections": [], "legendKey": null, "meetingTimes": [{"campusName": "LIVINGSTON", "startTime": "0640", "meetingDay": "TH", "meetingModeDesc": "LEC", "roomNumber": "253", "campusLocation": "3", "buildingCode": "TIL", "pmCode": "P", "baClassHours": null, "campusAbbrev": "LIV", "endTime": "0930", "meetingModeCode": "02"}], "honorPrograms": [], "instructors": [{"name": "CITRO, C"}], "printed": "Y", "examCode": "S", "campusCode": "NB", "sectionEligibility": "JUNIORS AND SENIORS ", "sessionDatePrintIndicator": "Y", "openStatus": true}], "campusCode": "NB", "coreCodes": [], "courseNotes": null, "title": "ASSET PRIC PORT ANL", "supplementCode": "  ", "subjectGroupNotes": null, "courseDescription": null, "synopsisUrl": null, "offeringUnitTitle": null, "openSections": 1, "credits": 3, "offeringUnitCode": "33", "preReqNotes": "(33:390:380 )", "unitNotes": "School 33 courses that previously held the subject code of 623 can now be found under the subject number 136, under the title Business Analytics and Information Technology.", "subjectNotes": "NO SPECIAL PERMISSION WILL BE GRANTED FOR RUTGERS BUSINESS SCHOOL-UNDERGRADUATE NB COURSES.", "courseNumber": "410", "expandedTitle": null, "subject": "390"}, {"sections": [{"minors": [], "sessionDates": null, "specialPermissionAddCode": null, "number": "01", "unitMajors": [], "subtitle": null, "specialPermissionDropCodeDescription": null, "specialPermissionAddCodeDescription": null, "subtopic": null, "majors": [{"code": "390", "isUnitCode": false, "isMajorCode": true}], "index": "07193", "sectionNotes": "FINANCE MAJS ONLY; NO SP NUMBERSGIVEN FOR THIS COURSE", "specialPermissionDropCode": null, "comments": [], "crossListedSections": [], "legendKey": null, "meetingTimes": [{"campusName": "LIVINGSTON", "startTime": "0320", "meetingDay": "TH", "meetingModeDesc": "LEC", "roomNumber": "5105", "campusLocation": "3", "buildingCode": "BRR", "pmCode": "P", "baClassHours": null, "campusAbbrev": "LIV", "endTime": "0440", "meetingModeCode": "02"}, {"campusName": "LIVINGSTON", "startTime": "0320", "meetingDay": "T", "meetingModeDesc": "LEC", "roomNumber": "5105", "campusLocation": "3", "buildingCode": "BRR", "pmCode": "P", "baClassHours": null, "campusAbbrev": "LIV", "endTime": "0440", "meetingModeCode": "02"}], "honorPrograms": [], "instructors": [{"name": "ZHONG, K"}], "printed": "Y", "examCode": "C", "campusCode": "NB", "sectionEligibility": "JUNIORS AND SENIORS ", "sessionDatePrintIndicator": "Y", "openStatus": false}, {"minors": [], "sessionDates": null, "specialPermissionAddCode": null, "number": "02", "unitMajors": [], "subtitle": null, "specialPermissionDropCodeDescription": null, "specialPermissionAddCodeDescription": null, "subtopic": null, "majors": [{"code": "390", "isUnitCode": false, "isMajorCode": true}], "index": "13485", "sectionNotes": "FINANCE MAJS ONLY; NO SPNUMBERS GIVEN FOR THIS COURSE", "specialPermissionDropCode": null, "comments": [], "crossListedSections": [], "legendKey": null, "meetingTimes": [{"campusName": "LIVINGSTON", "startTime": "0320", "meetingDay": "M", "meetingModeDesc": "LEC", "roomNumber": "5073", "campusLocation": "3", "buildingCode": "BRR", "pmCode": "P", "baClassHours": null, "campusAbbrev": "LIV", "endTime": "0440", "meetingModeCode": "02"}, {"campusName": "LIVINGSTON", "startTime": "0320", "meetingDay": "W", "meetingModeDesc": "LEC", "roomNumber": "5073", "campusLocation": "3", "buildingCode": "BRR", "pmCode": "P", "baClassHours": null, "campusAbbrev": "LIV", "endTime": "0440", "meetingModeCode": "02"}], "honorPrograms": [], "instructors": [{"name": "AMATI, A"}], "printed": "Y", "examCode": "C", "campusCode": "NB", "sectionEligibility": "JUNIORS AND SENIORS ", "sessionDatePrintIndicator": "Y", "openStatus": true}, {"minors": [], "sessionDates": null, "specialPermissionAddCode": null, "number": "03", "unitMajors": [], "subtitle": null, "specialPermissionDropCodeDescription": null, "specialPermissionAddCodeDescription": null, "subtopic": null, "majors": [{"code": "390", "isUnitCode": false, "isMajorCode": true}], "index": "18478", "sectionNotes": "FINANCE MAJORS ONLY;NO SP#S GIVEN FOR THIS COURSE", "specialPermissionDropCode": null, "comments": [], "crossListedSections": [], "legendKey": null, "meetingTimes": [{"campusName": "LIVINGSTON", "startTime": "0500", "meetingDay": "W", "meetingModeDesc": "LEC", "roomNumber": "5073", "campusLocation": "3", "buildingCode": "BRR", "pmCode": "P", "baClassHours": null, "campusAbbrev": "LIV", "endTime": "0620", "meetingModeCode": "02"}, {"campusName": "LIVINGSTON", "startTime": "0500", "meetingDay": "M", "meetingModeDesc": "LEC", "roomNumber": "5073", "campusLocation": "3", "buildingCode": "BRR", "pmCode": "P", "baClassHours": null, "campusAbbrev": "LIV", "endTime": "0620", "meetingModeCode": "02"}], "honorPrograms": [], "instructors": [{"name": "AMATI, A"}], "printed": "Y", "examCode": "C", "campusCode": "NB", "sectionEligibility": "JUNIORS AND SENIORS ", "sessionDatePrintIndicator": "Y", "openStatus": true}], "campusCode": "NB", "coreCodes": [], "courseNotes": null, "title": "DERIVATIVES", "supplementCode": "  ", "subjectGroupNotes": null, "courseDescription": null, "synopsisUrl": null, "offeringUnitTitle": null, "openSections": 2, "credits": 3, "offeringUnitCode": "33", "preReqNotes": "(33:390:380 )", "unitNotes": "School 33 courses that previously held the subject code of 623 can now be found under the subject number 136, under the title Business Analytics and Information Technology.", "subjectNotes": "NO SPECIAL PERMISSION WILL BE GRANTED FOR RUTGERS BUSINESS SCHOOL-UNDERGRADUATE NB COURSES.", "courseNumber": "420", "expandedTitle": "DERIVATIVES                                                                     ", "subject": "390"}, {"sections": [{"minors": [], "sessionDates": null, "specialPermissionAddCode": null, "number": "01", "unitMajors": [], "subtitle": null, "specialPermissionDropCodeDescription": null, "specialPermissionAddCodeDescription": null, "subtopic": null, "majors": [{"code": "390", "isUnitCode": false, "isMajorCode": true}], "index": "06582", "sectionNotes": "FINANCE MAJS ONLY; NO SP NUMBERSGIVEN FOR THIS COURSE", "specialPermissionDropCode": null, "comments": [{"code": "35", "description": "See online schedule for prereqs"}], "crossListedSections": [], "legendKey": null, "meetingTimes": [{"campusName": "LIVINGSTON", "startTime": "0320", "meetingDay": "T", "meetingModeDesc": "LEC", "roomNumber": "5101", "campusLocation": "3", "buildingCode": "BRR", "pmCode": "P", "baClassHours": null, "campusAbbrev": "LIV", "endTime": "0440", "meetingModeCode": "02"}, {"campusName": "LIVINGSTON", "startTime": "0320", "meetingDay": "TH", "meetingModeDesc": "LEC", "roomNumber": "5101", "campusLocation": "3", "buildingCode": "BRR", "pmCode": "P", "baClassHours": null, "campusAbbrev": "LIV", "endTime": "0440", "meetingModeCode": "02"}], "honorPrograms": [], "instructors": [{"name": "RICHTER, R"}], "printed": "Y", "examCode": "C", "campusCode": "NB", "sectionEligibility": "JUNIORS AND SENIORS ", "sessionDatePrintIndicator": "Y", "openStatus": false}, {"minors": [], "sessionDates": null, "specialPermissionAddCode": null, "number": "03", "unitMajors": [], "subtitle": null, "specialPermissionDropCodeDescription": null, "specialPermissionAddCodeDescription": null, "subtopic": null, "majors": [{"code": "390", "isUnitCode": false, "isMajorCode": true}], "index": "02458", "sectionNotes": "FINANCE MAJS ONLY; NO SP NUMBERSGIVEN FOR THIS COURSE", "specialPermissionDropCode": null, "comments": [{"code": "35", "description": "See online schedule for prereqs"}], "crossListedSections": [], "legendKey": null, "meetingTimes": [{"campusName": "LIVINGSTON", "startTime": "0640", "meetingDay": "TH", "meetingModeDesc": "LEC", "roomNumber": "5101", "campusLocation": "3", "buildingCode": "BRR", "pmCode": "P", "baClassHours": null, "campusAbbrev": "LIV", "endTime": "0930", "meetingModeCode": "02"}], "honorPrograms": [], "instructors": [{"name": "AQUILA, D"}, {"name": "RICHTER, R"}], "printed": "Y", "examCode": "S", "campusCode": "NB", "sectionEligibility": "JUNIORS AND SENIORS ", "sessionDatePrintIndicator": "Y", "openStatus": false}], "campusCode": "NB", "coreCodes": [], "courseNotes": null, "title": "WRKNG CAPITAL MGT", "supplementCode": "  ", "subjectGroupNotes": null, "courseDescription": null, "synopsisUrl": null, "offeringUnitTitle": null, "openSections": 0, "credits": 3, "offeringUnitCode": "33", "preReqNotes": "(33:390:300 )<em> OR </em>(33:390:310 )", "unitNotes": "School 33 courses that previously held the subject code of 623 can now be found under the subject number 136, under the title Business Analytics and Information Technology.", "subjectNotes": "NO SPECIAL PERMISSION WILL BE GRANTED FOR RUTGERS BUSINESS SCHOOL-UNDERGRADUATE NB COURSES.", "courseNumber": "430", "expandedTitle": null, "subject": "390"}, {"sections": [{"minors": [], "sessionDates": null, "specialPermissionAddCode": null, "number": "01", "unitMajors": [], "subtitle": null, "specialPermissionDropCodeDescription": null, "specialPermissionAddCodeDescription": null, "subtopic": null, "majors": [{"code": "390", "isUnitCode": false, "isMajorCode": true}], "index": "09267", "sectionNotes": "FINANCE MAJS ONLY; NO SP NUMBERSGIVEN FOR THIS COURSE", "specialPermissionDropCode": null, "comments": [], "crossListedSections": [], "legendKey": null, "meetingTimes": [{"campusName": "LIVINGSTON", "startTime": "0640", "meetingDay": "W", "meetingModeDesc": "LEC", "roomNumber": "5105", "campusLocation": "3", "buildingCode": "BRR", "pmCode": "P", "baClassHours": null, "campusAbbrev": "LIV", "endTime": "0930", "meetingModeCode": "02"}], "honorPrograms": [], "instructors": [{"name": "SOPRANZETTI, B"}], "printed": "Y", "examCode": "S", "campusCode": "NB", "sectionEligibility": "JUNIORS AND SENIORS ", "sessionDatePrintIndicator": "Y", "openStatus": false}, {"minors": [], "sessionDates": null, "specialPermissionAddCode": null, "number": "02", "unitMajors": [], "subtitle": null, "specialPermissionDropCodeDescription": null, "specialPermissionAddCodeDescription": null, "subtopic": null, "majors": [{"code": "390", "isUnitCode": false, "isMajorCode": true}], "index": "11852", "sectionNotes": null, "specialPermissionDropCode": null, "comments": [], "crossListedSections": [], "legendKey": null, "meetingTimes": [{"campusName": "LIVINGSTON", "startTime": "1020", "meetingDay": "W", "meetingModeDesc": "LEC", "roomNumber": "5101", "campusLocation": "3", "buildingCode": "BRR", "pmCode": "A", "baClassHours": null, "campusAbbrev": "LIV", "endTime": "0120", "meetingModeCode": "02"}], "honorPrograms": [], "instructors": [{"name": "SOPRANZETTI, B"}], "printed": "Y", "examCode": "C", "campusCode": "NB", "sectionEligibility": "JUNIORS AND SENIORS ", "sessionDatePrintIndicator": "Y", "openStatus": false}], "campusCode": "NB", "coreCodes": [], "courseNotes": null, "title": "ADV CORP FINANCE", "supplementCode": "  ", "subjectGroupNotes": null, "courseDescription": null, "synopsisUrl": null, "offeringUnitTitle": null, "openSections": 0, "credits": 3, "offeringUnitCode": "33", "preReqNotes": "(33:390:400 )", "unitNotes": "School 33 courses that previously held the subject code of 623 can now be found under the subject number 136, under the title Business Analytics and Information Technology.", "subjectNotes": "NO SPECIAL PERMISSION WILL BE GRANTED FOR RUTGERS BUSINESS SCHOOL-UNDERGRADUATE NB COURSES.", "courseNumber": "440", "expandedTitle": null, "subject": "390"}, {"sections": [{"minors": [], "sessionDates": null, "specialPermissionAddCode": "03", "number": "01", "unitMajors": [], "subtitle": null, "specialPermissionDropCodeDescription": null, "specialPermissionAddCodeDescription": "Department staff", "subtopic": null, "majors": [{"code": "390", "isUnitCode": false, "isMajorCode": true}], "index": "02049", "sectionNotes": "FINANCE MAJS ONLY; NO SP NUMBERSGIVEN FOR THIS COURSE", "specialPermissionDropCode": null, "comments": [{"code": "35", "description": "See online schedule for prereqs"}], "crossListedSections": [], "legendKey": null, "meetingTimes": [{"campusName": null, "startTime": null, "meetingDay": null, "meetingModeDesc": "PROJ-IND", "roomNumber": null, "campusLocation": null, "buildingCode": null, "pmCode": null, "baClassHours": "B", "campusAbbrev": null, "endTime": null, "meetingModeCode": "19"}], "honorPrograms": [], "instructors": [], "printed": "Y", "examCode": "A", "campusCode": "NB", "sectionEligibility": "JUNIORS AND SENIORS ", "sessionDatePrintIndicator": "Y", "openStatus": true}], "campusCode": "NB", "coreCodes": [], "courseNotes": null, "title": "RESEARCH IN FINANCE", "supplementCode": "  ", "subjectGroupNotes": null, "courseDescription": null, "synopsisUrl": null, "offeringUnitTitle": null, "openSections": 1, "credits": null, "offeringUnitCode": "33", "preReqNotes": "(33:390:300 )<em> OR </em>(33:390:310 )", "unitNotes": "School 33 courses that previously held the subject code of 623 can now be found under the subject number 136, under the title Business Analytics and Information Technology.", "subjectNotes": "NO SPECIAL PERMISSION WILL BE GRANTED FOR RUTGERS BUSINESS SCHOOL-UNDERGRADUATE NB COURSES.", "courseNumber": "480", "expandedTitle": null, "subject": "390"}, {"sections": [{"minors": [], "sessionDates": null, "specialPermissionAddCode": null, "number": "01", "unitMajors": [], "subtitle": "FIXED INCOME                            ", "specialPermissionDropCodeDescription": null, "specialPermissionAddCodeDescription": null, "subtopic": null, "majors": [{"code": "390", "isUnitCode": false, "isMajorCode": true}], "index": "08307", "sectionNotes": null, "specialPermissionDropCode": null, "comments": [{"code": "35", "description": "See online schedule for prereqs"}], "crossListedSections": [], "legendKey": null, "meetingTimes": [{"campusName": "LIVINGSTON", "startTime": "1200", "meetingDay": "TH", "meetingModeDesc": "LEC", "roomNumber": "4071", "campusLocation": "3", "buildingCode": "BRR", "pmCode": "P", "baClassHours": null, "campusAbbrev": "LIV", "endTime": "0120", "meetingModeCode": "02"}, {"campusName": "LIVINGSTON", "startTime": "1200", "meetingDay": "M", "meetingModeDesc": "LEC", "roomNumber": "4071", "campusLocation": "3", "buildingCode": "BRR", "pmCode": "P", "baClassHours": null, "campusAbbrev": "LIV", "endTime": "0120", "meetingModeCode": "02"}], "honorPrograms": [], "instructors": [{"name": "NG, FRANCIS"}], "printed": "Y", "examCode": "C", "campusCode": "NB", "sectionEligibility": "JUNIORS AND SENIORS ", "sessionDatePrintIndicator": "Y", "openStatus": true}], "campusCode": "NB", "coreCodes": [], "courseNotes": null, "title": "FIXED INCOME", "supplementCode": "  ", "subjectGroupNotes": null, "courseDescription": null, "synopsisUrl": null, "offeringUnitTitle": null, "openSections": 1, "credits": 3, "offeringUnitCode": "33", "preReqNotes": "(33:390:380 )", "unitNotes": "School 33 courses that previously held the subject code of 623 can now be found under the subject number 136, under the title Business Analytics and Information Technology.", "subjectNotes": "NO SPECIAL PERMISSION WILL BE GRANTED FOR RUTGERS BUSINESS SCHOOL-UNDERGRADUATE NB COURSES.", "courseNumber": "490", "expandedTitle": null, "subject": "390"}, {"sections": [{"minors": [], "sessionDates": null, "specialPermissionAddCode": "07", "number": "H1", "unitMajors": [], "subtitle": null, "specialPermissionDropCodeDescription": null, "specialPermissionAddCodeDescription": "Dean - School of Business", "subtopic": null, "majors": [], "index": "09952", "sectionNotes": "PERMISSION REQUIRED FROM RBSUNDERGRAD DEAN'S OFFICE", "specialPermissionDropCode": null, "comments": [{"code": "87", "description": "For Honors Students only"}], "crossListedSections": [], "legendKey": null, "meetingTimes": [{"campusName": null, "startTime": null, "meetingDay": null, "meetingModeDesc": "LEC", "roomNumber": null, "campusLocation": null, "buildingCode": null, "pmCode": null, "baClassHours": "B", "campusAbbrev": null, "endTime": null, "meetingModeCode": "02"}], "honorPrograms": [{"code": "A"}, {"code": "7"}, {"code": "6"}, {"code": "5"}, {"code": "B"}], "instructors": [], "printed": "Y", "examCode": "A", "campusCode": "NB", "sectionEligibility": null, "sessionDatePrintIndicator": "Y", "openStatus": true}], "campusCode": "NB", "coreCodes": [], "courseNotes": null, "title": "HONORS PROG FINANCE", "supplementCode": "  ", "subjectGroupNotes": null, "courseDescription": null, "synopsisUrl": null, "offeringUnitTitle": null, "openSections": 1, "credits": 3, "offeringUnitCode": "33", "preReqNotes": null, "unitNotes": "School 33 courses that previously held the subject code of 623 can now be found under the subject number 136, under the title Business Analytics and Information Technology.", "subjectNotes": "NO SPECIAL PERMISSION WILL BE GRANTED FOR RUTGERS BUSINESS SCHOOL-UNDERGRADUATE NB COURSES.", "courseNumber": "495", "expandedTitle": null, "subject": "390"}, {"sections": [{"minors": [], "sessionDates": null, "specialPermissionAddCode": "07", "number": "H1", "unitMajors": [], "subtitle": null, "specialPermissionDropCodeDescription": null, "specialPermissionAddCodeDescription": "Dean - School of Business", "subtopic": null, "majors": [], "index": "15366", "sectionNotes": "PERMISSION REQUIRED FROM RBSUNDERGRAD DEAN'S OFFICE", "specialPermissionDropCode": null, "comments": [{"code": "87", "description": "For Honors Students only"}], "crossListedSections": [], "legendKey": null, "meetingTimes": [{"campusName": null, "startTime": null, "meetingDay": null, "meetingModeDesc": "PROJ-IND", "roomNumber": null, "campusLocation": null, "buildingCode": null, "pmCode": null, "baClassHours": "B", "campusAbbrev": null, "endTime": null, "meetingModeCode": "19"}], "honorPrograms": [], "instructors": [], "printed": "Y", "examCode": "A", "campusCode": "NB", "sectionEligibility": null, "sessionDatePrintIndicator": "Y", "openStatus": true}], "campusCode": "NB", "coreCodes": [], "courseNotes": null, "title": "HONORS PROG FINANCE", "supplementCode": "  ", "subjectGroupNotes": null, "courseDescription": null, "synopsisUrl": null, "offeringUnitTitle": null, "openSections": 1, "credits": 3, "offeringUnitCode": "33", "preReqNotes": null, "unitNotes": "School 33 courses that previously held the subject code of 623 can now be found under the subject number 136, under the title Business Analytics and Information Technology.", "subjectNotes": "NO SPECIAL PERMISSION WILL BE GRANTED FOR RUTGERS BUSINESS SCHOOL-UNDERGRADUATE NB COURSES.", "courseNumber": "496", "expandedTitle": null, "subject": "390"}]