[{"sections": [{"minors": [], "sessionDates": null, "specialPermissionAddCode": null, "number": "01", "unitMajors": [], "subtitle": null, "specialPermissionDropCodeDescription": null, "specialPermissionAddCodeDescription": null, "subtopic": null, "majors": [], "index": "17939", "sectionNotes": null, "specialPermissionDropCode": null, "comments": [], "crossListedSections": [], "legendKey": null, "meetingTimes": [{"campusName": "DOUGLAS/COOK", "startTime": "0215", "meetingDay": "TH", "meetingModeDesc": "LEC", "roomNumber": "110", "campusLocation": "4", "buildingCode": "CDL", "pmCode": "P", "baClassHours": null, "campusAbbrev": "D/C", "endTime": "0335", "meetingModeCode": "02"}, {"campusName": "DOUGLAS/COOK", "startTime": "0215", "meetingDay": "T", "meetingModeDesc": "LEC", "roomNumber": "110", "campusLocation": "4", "buildingCode": "CDL", "pmCode": "P", "baClassHours": null, "campusAbbrev": "D/C", "endTime": "0335", "meetingModeCode": "02"}], "honorPrograms": [], "instructors": [{"name": "RHINEY, K."}], "printed": "Y", "examCode": "C", "campusCode": "NB", "sectionEligibility": null, "sessionDatePrintIndicator": "Y", "openStatus": true}], "campusCode": "NB", "coreCodes": [{"coreCodeReferenceId": "15", "term": "1", "code": "21C", "description": "21st Century Challenges", "effective": "20171", "coreCode": "21C", "offeringUnitCode": "01", "offeringUnitCampus": "NB", "course": "101", "supplement": "  ", "coreCodeDescription": "21st Century Challenges", "lastUpdated": 1468423713000, "year": "2017", "id": "2017101381101  15", "unit": "01", "subject": "381"}], "courseNotes": null, "title": "INTRO ENVIRN STUDIES", "supplementCode": "  ", "subjectGroupNotes": null, "courseDescription": null, "synopsisUrl": null, "offeringUnitTitle": null, "openSections": 1, "credits": 3, "offeringUnitCode": "01", "preReqNotes": null, "unitNotes": null, "subjectNotes": null, "courseNumber": "101", "expandedTitle": "INTRODUCTION TO ENVIRONMENTAL STUDIES                                           ", "subject": "381"}]