[{"sections": [{"minors": [], "sessionDates": null, "specialPermissionAddCode": null, "number": "01", "unitMajors": [], "subtitle": null, "specialPermissionDropCodeDescription": null, "specialPermissionAddCodeDescription": null, "subtopic": null, "majors": [], "index": "20523", "sectionNotes": null, "specialPermissionDropCode": null, "comments": [], "crossListedSections": [], "legendKey": null, "meetingTimes": [{"campusName": null, "startTime": null, "meetingDay": null, "meetingModeDesc": "LEC", "roomNumber": null, "campusLocation": null, "buildingCode": null, "pmCode": null, "baClassHours": "B", "campusAbbrev": null, "endTime": null, "meetingModeCode": "02"}], "honorPrograms": [], "instructors": [], "printed": "N", "examCode": "A", "campusCode": "NB", "sectionEligibility": null, "sessionDatePrintIndicator": "Y", "openStatus": true}], "campusCode": "NB", "coreCodes": [], "courseNotes": null, "title": "NEEDS PLACEMENT TEST", "supplementCode": "  ", "subjectGroupNotes": null, "courseDescription": null, "synopsisUrl": "http://reell.rutgers.edu/courses", "offeringUnitTitle": null, "openSections": 1, "credits": 3, "offeringUnitCode": "01", "preReqNotes": null, "unitNotes": null, "subjectNotes": null, "courseNumber": "005", "expandedTitle": null, "subject": "787"}, {"sections": [{"minors": [], "sessionDates": null, "specialPermissionAddCode": null, "number": "01", "unitMajors": [], "subtitle": null, "specialPermissionDropCodeDescription": null, "specialPermissionAddCodeDescription": null, "subtopic": null, "majors": [], "index": "05870", "sectionNotes": "OPEN TO STUDENTS WITH NO PRIORKNOWLEDGE OF POLISH. STUDENTSWITH PRIOR KNOWLEDGE MUST TAKEPLACEMENT TEST REELL.RUTGERS.EDU", "specialPermissionDropCode": null, "comments": [], "crossListedSections": [], "legendKey": null, "meetingTimes": [{"campusName": "COLLEGE AVENUE", "startTime": "0110", "meetingDay": "T", "meetingModeDesc": "LEC", "roomNumber": "2150", "campusLocation": "1", "buildingCode": "AB", "pmCode": "P", "baClassHours": null, "campusAbbrev": "CAC", "endTime": "0230", "meetingModeCode": "02"}, {"campusName": "COLLEGE AVENUE", "startTime": "0110", "meetingDay": "TH", "meetingModeDesc": "LEC", "roomNumber": "2150", "campusLocation": "1", "buildingCode": "AB", "pmCode": "P", "baClassHours": null, "campusAbbrev": "CAC", "endTime": "0230", "meetingModeCode": "02"}, {"campusName": "COLLEGE AVENUE", "startTime": "0110", "meetingDay": "M", "meetingModeDesc": "LEC", "roomNumber": "2150", "campusLocation": "1", "buildingCode": "AB", "pmCode": "P", "baClassHours": null, "campusAbbrev": "CAC", "endTime": "0230", "meetingModeCode": "02"}], "honorPrograms": [], "instructors": [{"name": "MANDECKI, W."}], "printed": "Y", "examCode": "C", "campusCode": "NB", "sectionEligibility": null, "sessionDatePrintIndicator": "Y", "openStatus": true}], "campusCode": "NB", "coreCodes": [], "courseNotes": null, "title": "ELEMENTARY POLISH I", "supplementCode": "  ", "subjectGroupNotes": null, "courseDescription": null, "synopsisUrl": "http://reell.rutgers.edu/courses", "offeringUnitTitle": null, "openSections": 1, "credits": 4, "offeringUnitCode": "01", "preReqNotes": null, "unitNotes": null, "subjectNotes": null, "courseNumber": "101", "expandedTitle": "ELEMENTARY POLISH I                                                             ", "subject": "787"}, {"sections": [{"minors": [], "sessionDates": null, "specialPermissionAddCode": null, "number": "01", "unitMajors": [], "subtitle": null, "specialPermissionDropCodeDescription": null, "specialPermissionAddCodeDescription": null, "subtopic": null, "majors": [], "index": "13596", "sectionNotes": "PREREQ: 01:787:102 OR PERMISSIONOR PLACEMENT.", "specialPermissionDropCode": null, "comments": [], "crossListedSections": [], "legendKey": null, "meetingTimes": [{"campusName": "COLLEGE AVENUE", "startTime": "0250", "meetingDay": "M", "meetingModeDesc": "LEC", "roomNumber": "2250", "campusLocation": "1", "buildingCode": "AB", "pmCode": "P", "baClassHours": null, "campusAbbrev": "CAC", "endTime": "0410", "meetingModeCode": "02"}, {"campusName": "COLLEGE AVENUE", "startTime": "0250", "meetingDay": "TH", "meetingModeDesc": "LEC", "roomNumber": "2250", "campusLocation": "1", "buildingCode": "AB", "pmCode": "P", "baClassHours": null, "campusAbbrev": "CAC", "endTime": "0410", "meetingModeCode": "02"}, {"campusName": "COLLEGE AVENUE", "startTime": "0250", "meetingDay": "T", "meetingModeDesc": "LEC", "roomNumber": "2250", "campusLocation": "1", "buildingCode": "AB", "pmCode": "P", "baClassHours": null, "campusAbbrev": "CAC", "endTime": "0410", "meetingModeCode": "02"}], "honorPrograms": [], "instructors": [{"name": "MANDECKI, W."}], "printed": "Y", "examCode": "C", "campusCode": "NB", "sectionEligibility": null, "sessionDatePrintIndicator": "Y", "openStatus": true}], "campusCode": "NB", "coreCodes": [], "courseNotes": null, "title": "INTER POLISH I", "supplementCode": "  ", "subjectGroupNotes": null, "courseDescription": null, "synopsisUrl": "http://reell.rutgers.edu/courses", "offeringUnitTitle": null, "openSections": 1, "credits": 4, "offeringUnitCode": "01", "preReqNotes": "(01:787:102 )", "unitNotes": null, "subjectNotes": null, "courseNumber": "201", "expandedTitle": "INTERMEDIATE POLISH I                                                           ", "subject": "787"}, {"sections": [{"minors": [], "sessionDates": null, "specialPermissionAddCode": "03", "number": "01", "unitMajors": [], "subtitle": null, "specialPermissionDropCodeDescription": null, "specialPermissionAddCodeDescription": "Department staff", "subtopic": null, "majors": [], "index": "20848", "sectionNotes": "COURSE WILL ALSO INCLUDE 1 HOURCONVERSATION SESSION, TBA.", "specialPermissionDropCode": null, "comments": [], "crossListedSections": [], "legendKey": null, "meetingTimes": [{"campusName": "COLLEGE AVENUE", "startTime": "1230", "meetingDay": "M", "meetingModeDesc": "LEC", "roomNumber": "5141", "campusLocation": "1", "buildingCode": "AB", "pmCode": "P", "baClassHours": null, "campusAbbrev": "CAC", "endTime": "0130", "meetingModeCode": "02"}, {"campusName": "COLLEGE AVENUE", "startTime": "1230", "meetingDay": "F", "meetingModeDesc": "LEC", "roomNumber": "5141", "campusLocation": "1", "buildingCode": "AB", "pmCode": "P", "baClassHours": null, "campusAbbrev": "CAC", "endTime": "0130", "meetingModeCode": "02"}, {"campusName": "COLLEGE AVENUE", "startTime": "1230", "meetingDay": "W", "meetingModeDesc": "LEC", "roomNumber": "5141", "campusLocation": "1", "buildingCode": "AB", "pmCode": "P", "baClassHours": null, "campusAbbrev": "CAC", "endTime": "0130", "meetingModeCode": "02"}], "honorPrograms": [], "instructors": [], "printed": "Y", "examCode": "C", "campusCode": "NB", "sectionEligibility": null, "sessionDatePrintIndicator": "Y", "openStatus": true}], "campusCode": "NB", "coreCodes": [], "courseNotes": null, "title": "ADVANCED POLISH", "supplementCode": "  ", "subjectGroupNotes": null, "courseDescription": null, "synopsisUrl": "http://reell.rutgers.edu/courses", "offeringUnitTitle": null, "openSections": 1, "credits": 3, "offeringUnitCode": "01", "preReqNotes": "(01:787:202 )", "unitNotes": null, "subjectNotes": null, "courseNumber": "401", "expandedTitle": null, "subject": "787"}]