[{"sections": [{"minors": [], "sessionDates": null, "specialPermissionAddCode": null, "number": "01", "unitMajors": [], "subtitle": null, "specialPermissionDropCodeDescription": null, "specialPermissionAddCodeDescription": null, "subtopic": null, "majors": [], "index": "20526", "sectionNotes": null, "specialPermissionDropCode": null, "comments": [], "crossListedSections": [], "legendKey": null, "meetingTimes": [{"campusName": null, "startTime": null, "meetingDay": null, "meetingModeDesc": "LEC", "roomNumber": null, "campusLocation": null, "buildingCode": null, "pmCode": null, "baClassHours": "B", "campusAbbrev": null, "endTime": null, "meetingModeCode": "02"}], "honorPrograms": [], "instructors": [], "printed": "N", "examCode": "A", "campusCode": "NB", "sectionEligibility": null, "sessionDatePrintIndicator": "Y", "openStatus": true}], "campusCode": "NB", "coreCodes": [], "courseNotes": null, "title": "NEEDS PLACEMENT TEST", "supplementCode": "  ", "subjectGroupNotes": null, "courseDescription": null, "synopsisUrl": "http://span-port.rutgers.edu/course-synopses", "offeringUnitTitle": null, "openSections": 1, "credits": 3, "offeringUnitCode": "01", "preReqNotes": null, "unitNotes": null, "subjectNotes": "SEE PORTUGUESE(810) FOR ADDITIONAL COURSES. \r\n\r\nFOR ONLINE COURSES SELECT ONLINE COURSES UNDER COURSE TYPE TO SEE COURSE OFFERINGS.", "courseNumber": "005", "expandedTitle": null, "subject": "940"}, {"sections": [{"minors": [], "sessionDates": null, "specialPermissionAddCode": null, "number": "01", "unitMajors": [], "subtitle": null, "specialPermissionDropCodeDescription": null, "specialPermissionAddCodeDescription": null, "subtopic": null, "majors": [], "index": "07240", "sectionNotes": "COMMON HOUR EXAM REQUIREDFOR STUDENTS 0-1 YRS HS SPANISH;NON-NATIVE.", "specialPermissionDropCode": null, "comments": [{"code": "37", "description": "CHE sched at scheduling.rutgers.edu"}], "crossListedSections": [], "legendKey": null, "meetingTimes": [{"campusName": "COLLEGE AVENUE", "startTime": "1130", "meetingDay": "M", "meetingModeDesc": "LEC", "roomNumber": "204", "campusLocation": "1", "buildingCode": "MU", "pmCode": "A", "baClassHours": null, "campusAbbrev": "CAC", "endTime": "1250", "meetingModeCode": "02"}, {"campusName": "COLLEGE AVENUE", "startTime": "1130", "meetingDay": "TH", "meetingModeDesc": "LEC", "roomNumber": "204", "campusLocation": "1", "buildingCode": "MU", "pmCode": "A", "baClassHours": null, "campusAbbrev": "CAC", "endTime": "1250", "meetingModeCode": "02"}, {"campusName": "COLLEGE AVENUE", "startTime": "1130", "meetingDay": "W", "meetingModeDesc": "RECIT", "roomNumber": "204", "campusLocation": "1", "buildingCode": "MU", "pmCode": "A", "baClassHours": null, "campusAbbrev": "CAC", "endTime": "1250", "meetingModeCode": "03"}], "honorPrograms": [], "instructors": [], "printed": "Y", "examCode": "D", "campusCode": "NB", "sectionEligibility": null, "sessionDatePrintIndicator": "Y", "openStatus": true}, {"minors": [], "sessionDates": null, "specialPermissionAddCode": null, "number": "03", "unitMajors": [], "subtitle": null, "specialPermissionDropCodeDescription": null, "specialPermissionAddCodeDescription": null, "subtopic": null, "majors": [], "index": "11916", "sectionNotes": "COMMON HOUR EXAM REQUIREDFOR STUDENTS 0-1 YRS HS SPANISH;NON-NATIVE.", "specialPermissionDropCode": null, "comments": [{"code": "37", "description": "CHE sched at scheduling.rutgers.edu"}], "crossListedSections": [], "legendKey": null, "meetingTimes": [{"campusName": "DOUGLAS/COOK", "startTime": "0915", "meetingDay": "TH", "meetingModeDesc": "LEC", "roomNumber": "132", "campusLocation": "4", "buildingCode": "HCK", "pmCode": "A", "baClassHours": null, "campusAbbrev": "D/C", "endTime": "1035", "meetingModeCode": "02"}, {"campusName": "DOUGLAS/COOK", "startTime": "0915", "meetingDay": "M", "meetingModeDesc": "LEC", "roomNumber": "132", "campusLocation": "4", "buildingCode": "HCK", "pmCode": "A", "baClassHours": null, "campusAbbrev": "D/C", "endTime": "1035", "meetingModeCode": "02"}, {"campusName": "DOUGLAS/COOK", "startTime": "0915", "meetingDay": "W", "meetingModeDesc": "LEC", "roomNumber": "132", "campusLocation": "4", "buildingCode": "HCK", "pmCode": "A", "baClassHours": null, "campusAbbrev": "D/C", "endTime": "1035", "meetingModeCode": "02"}], "honorPrograms": [], "instructors": [], "printed": "Y", "examCode": "D", "campusCode": "NB", "sectionEligibility": null, "sessionDatePrintIndicator": "Y", "openStatus": true}, {"minors": [], "sessionDates": null, "specialPermissionAddCode": null, "number": "04", "unitMajors": [], "subtitle": null, "specialPermissionDropCodeDescription": null, "specialPermissionAddCodeDescription": null, "subtopic": null, "majors": [], "index": "03187", "sectionNotes": "COMMON HOUR EXAM REQUIREDFOR STUDENTS 0-1 YRS HS SPANISH;NON-NATIVE.", "specialPermissionDropCode": null, "comments": [{"code": "37", "description": "CHE sched at scheduling.rutgers.edu"}], "crossListedSections": [], "legendKey": null, "meetingTimes": [{"campusName": "DOUGLAS/COOK", "startTime": "0535", "meetingDay": "TH", "meetingModeDesc": "LEC", "roomNumber": "127", "campusLocation": "4", "buildingCode": "HCK", "pmCode": "P", "baClassHours": null, "campusAbbrev": "D/C", "endTime": "0725", "meetingModeCode": "02"}, {"campusName": "DOUGLAS/COOK", "startTime": "0535", "meetingDay": "T", "meetingModeDesc": "LEC", "roomNumber": "127", "campusLocation": "4", "buildingCode": "HCK", "pmCode": "P", "baClassHours": null, "campusAbbrev": "D/C", "endTime": "0725", "meetingModeCode": "02"}], "honorPrograms": [], "instructors": [], "printed": "Y", "examCode": "D", "campusCode": "NB", "sectionEligibility": null, "sessionDatePrintIndicator": "Y", "openStatus": true}, {"minors": [], "sessionDates": null, "specialPermissionAddCode": null, "number": "05", "unitMajors": [], "subtitle": null, "specialPermissionDropCodeDescription": null, "specialPermissionAddCodeDescription": null, "subtopic": null, "majors": [], "index": "00453", "sectionNotes": "COMMON HOUR EXAM REQUIREDFOR STUDENTS 0-1 YRS HS SPANISH;NON-NATIVE.", "specialPermissionDropCode": null, "comments": [{"code": "37", "description": "CHE sched at scheduling.rutgers.edu"}], "crossListedSections": [], "legendKey": null, "meetingTimes": [{"campusName": "COLLEGE AVENUE", "startTime": "0740", "meetingDay": "M", "meetingModeDesc": "LEC", "roomNumber": "104", "campusLocation": "1", "buildingCode": "SC", "pmCode": "P", "baClassHours": null, "campusAbbrev": "CAC", "endTime": "0930", "meetingModeCode": "02"}, {"campusName": "COLLEGE AVENUE", "startTime": "0740", "meetingDay": "W", "meetingModeDesc": "LEC", "roomNumber": "104", "campusLocation": "1", "buildingCode": "SC", "pmCode": "P", "baClassHours": null, "campusAbbrev": "CAC", "endTime": "0930", "meetingModeCode": "02"}], "honorPrograms": [], "instructors": [], "printed": "Y", "examCode": "D", "campusCode": "NB", "sectionEligibility": null, "sessionDatePrintIndicator": "Y", "openStatus": true}, {"minors": [], "sessionDates": null, "specialPermissionAddCode": null, "number": "90", "unitMajors": [], "subtitle": null, "specialPermissionDropCodeDescription": null, "specialPermissionAddCodeDescription": null, "subtopic": null, "majors": [], "index": "09456", "sectionNotes": "FOR STUDENTS 0-1 YRS HS SPANISHNON-NATIVE.", "specialPermissionDropCode": null, "comments": [{"code": "60", "description": "Go to http://Sakai.rutgers.edu"}, {"code": "61", "description": "$100 Online Course Support fee"}, {"code": "56", "description": "Online Course"}], "crossListedSections": [], "legendKey": null, "meetingTimes": [{"campusName": null, "startTime": null, "meetingDay": null, "meetingModeDesc": "ONLINE INSTRUCTION(INTERNET)", "roomNumber": null, "campusLocation": null, "buildingCode": null, "pmCode": null, "baClassHours": "B", "campusAbbrev": null, "endTime": null, "meetingModeCode": "90"}], "honorPrograms": [], "instructors": [{"name": "MILLAN, M"}], "printed": "Y", "examCode": "A", "campusCode": "NB", "sectionEligibility": null, "sessionDatePrintIndicator": "Y", "openStatus": false}, {"minors": [], "sessionDates": null, "specialPermissionAddCode": null, "number": "91", "unitMajors": [], "subtitle": null, "specialPermissionDropCodeDescription": null, "specialPermissionAddCodeDescription": null, "subtopic": null, "majors": [], "index": "09457", "sectionNotes": "FOR STUDENTS 0-1 YRS HS SPANISHNON-NATIVE.", "specialPermissionDropCode": null, "comments": [{"code": "60", "description": "Go to http://Sakai.rutgers.edu"}, {"code": "61", "description": "$100 Online Course Support fee"}, {"code": "56", "description": "Online Course"}], "crossListedSections": [], "legendKey": null, "meetingTimes": [{"campusName": null, "startTime": null, "meetingDay": null, "meetingModeDesc": "ONLINE INSTRUCTION(INTERNET)", "roomNumber": null, "campusLocation": null, "buildingCode": null, "pmCode": null, "baClassHours": "B", "campusAbbrev": null, "endTime": null, "meetingModeCode": "90"}], "honorPrograms": [], "instructors": [{"name": "MILLAN, M"}], "printed": "Y", "examCode": "A", "campusCode": "NB", "sectionEligibility": null, "sessionDatePrintIndicator": "Y", "openStatus": true}], "campusCode": "NB", "coreCodes": [], "courseNotes": "FOR ALL SECTIONS: NOT OPEN TO THOSE WHO HAVE TAKEN 2 OR MORE YEARS H.S. SPANISH OR TO NATIVE SPEAKERS OF SPANISH.  \r\n", "title": "ELEMENTARY SPANISH", "supplementCode": "  ", "subjectGroupNotes": null, "courseDescription": null, "synopsisUrl": "http://span-port.rutgers.edu/course-synopses", "offeringUnitTitle": null, "openSections": 5, "credits": 4, "offeringUnitCode": "01", "preReqNotes": null, "unitNotes": null, "subjectNotes": "SEE PORTUGUESE(810) FOR ADDITIONAL COURSES. \r\n\r\nFOR ONLINE COURSES SELECT ONLINE COURSES UNDER COURSE TYPE TO SEE COURSE OFFERINGS.", "courseNumber": "101", "expandedTitle": null, "subject": "940"}, {"sections": [{"minors": [], "sessionDates": null, "specialPermissionAddCode": null, "number": "01", "unitMajors": [], "subtitle": null, "specialPermissionDropCodeDescription": null, "specialPermissionAddCodeDescription": null, "subtopic": null, "majors": [], "index": "03293", "sectionNotes": null, "specialPermissionDropCode": null, "comments": [{"code": "37", "description": "CHE sched at scheduling.rutgers.edu"}], "crossListedSections": [], "legendKey": null, "meetingTimes": [{"campusName": "COLLEGE AVENUE", "startTime": "0540", "meetingDay": "W", "meetingModeDesc": "LEC", "roomNumber": "3100", "campusLocation": "1", "buildingCode": "AB", "pmCode": "P", "baClassHours": null, "campusAbbrev": "CAC", "endTime": "0730", "meetingModeCode": "02"}, {"campusName": "COLLEGE AVENUE", "startTime": "0540", "meetingDay": "M", "meetingModeDesc": "LEC", "roomNumber": "3100", "campusLocation": "1", "buildingCode": "AB", "pmCode": "P", "baClassHours": null, "campusAbbrev": "CAC", "endTime": "0730", "meetingModeCode": "02"}], "honorPrograms": [], "instructors": [], "printed": "Y", "examCode": "D", "campusCode": "NB", "sectionEligibility": null, "sessionDatePrintIndicator": "Y", "openStatus": true}, {"minors": [], "sessionDates": null, "specialPermissionAddCode": null, "number": "90", "unitMajors": [], "subtitle": null, "specialPermissionDropCodeDescription": null, "specialPermissionAddCodeDescription": null, "subtopic": null, "majors": [], "index": "09458", "sectionNotes": null, "specialPermissionDropCode": null, "comments": [{"code": "56", "description": "Online Course"}, {"code": "60", "description": "Go to http://Sakai.rutgers.edu"}, {"code": "61", "description": "$100 Online Course Support fee"}], "crossListedSections": [], "legendKey": null, "meetingTimes": [{"campusName": null, "startTime": null, "meetingDay": null, "meetingModeDesc": "ONLINE INSTRUCTION(INTERNET)", "roomNumber": null, "campusLocation": null, "buildingCode": null, "pmCode": null, "baClassHours": "B", "campusAbbrev": null, "endTime": null, "meetingModeCode": "90"}], "honorPrograms": [], "instructors": [], "printed": "Y", "examCode": "A", "campusCode": "NB", "sectionEligibility": null, "sessionDatePrintIndicator": "Y", "openStatus": false}], "campusCode": "NB", "coreCodes": [], "courseNotes": "FOR ALL SECTIONS: NOT OPEN TO THOSE WHO HAVE TAKEN 2 OR MORE YEARS H.S. SPANISH OR TO NATIVE SPEAKERS OF SPANISH. ", "title": "ELEMENTARY SPANISH", "supplementCode": "  ", "subjectGroupNotes": null, "courseDescription": null, "synopsisUrl": "http://span-port.rutgers.edu/course-synopses", "offeringUnitTitle": null, "openSections": 1, "credits": 4, "offeringUnitCode": "01", "preReqNotes": "(01:940:101 )", "unitNotes": null, "subjectNotes": "SEE PORTUGUESE(810) FOR ADDITIONAL COURSES. \r\n\r\nFOR ONLINE COURSES SELECT ONLINE COURSES UNDER COURSE TYPE TO SEE COURSE OFFERINGS.", "courseNumber": "102", "expandedTitle": null, "subject": "940"}, {"sections": [{"minors": [], "sessionDates": null, "specialPermissionAddCode": null, "number": "01", "unitMajors": [], "subtitle": null, "specialPermissionDropCodeDescription": null, "specialPermissionAddCodeDescription": null, "subtopic": null, "majors": [], "index": "07237", "sectionNotes": "COMMON HOUR EXAM REQUIREDGO TO SCHEDULING.RUTGERS.EDUOPEN BY PLACEMENT EXAM ORPERMISSION OF DEPT.", "specialPermissionDropCode": null, "comments": [], "crossListedSections": [], "legendKey": null, "meetingTimes": [{"campusName": "COLLEGE AVENUE", "startTime": "0810", "meetingDay": "M", "meetingModeDesc": "LEC", "roomNumber": "120", "campusLocation": "1", "buildingCode": "SC", "pmCode": "A", "baClassHours": null, "campusAbbrev": "CAC", "endTime": "0930", "meetingModeCode": "02"}, {"campusName": "COLLEGE AVENUE", "startTime": "0810", "meetingDay": "TH", "meetingModeDesc": "LEC", "roomNumber": "120", "campusLocation": "1", "buildingCode": "SC", "pmCode": "A", "baClassHours": null, "campusAbbrev": "CAC", "endTime": "0930", "meetingModeCode": "02"}], "honorPrograms": [], "instructors": [], "printed": "Y", "examCode": "D", "campusCode": "NB", "sectionEligibility": null, "sessionDatePrintIndicator": "Y", "openStatus": true}, {"minors": [], "sessionDates": null, "specialPermissionAddCode": null, "number": "04", "unitMajors": [], "subtitle": null, "specialPermissionDropCodeDescription": null, "specialPermissionAddCodeDescription": null, "subtopic": null, "majors": [], "index": "08081", "sectionNotes": "COMMON HOUR EXAM REQUIREDGO TO SCHEDULING.RUTGERS.EDUOPEN BY PLACEMENT EXAM ORPERMISSION OF DEPT.", "specialPermissionDropCode": null, "comments": [], "crossListedSections": [], "legendKey": null, "meetingTimes": [{"campusName": "COLLEGE AVENUE", "startTime": "0110", "meetingDay": "W", "meetingModeDesc": "LEC", "roomNumber": "210", "campusLocation": "1", "buildingCode": "MU", "pmCode": "P", "baClassHours": null, "campusAbbrev": "CAC", "endTime": "0230", "meetingModeCode": "02"}, {"campusName": "COLLEGE AVENUE", "startTime": "0110", "meetingDay": "M", "meetingModeDesc": "LEC", "roomNumber": "210", "campusLocation": "1", "buildingCode": "MU", "pmCode": "P", "baClassHours": null, "campusAbbrev": "CAC", "endTime": "0230", "meetingModeCode": "02"}], "honorPrograms": [], "instructors": [], "printed": "Y", "examCode": "D", "campusCode": "NB", "sectionEligibility": null, "sessionDatePrintIndicator": "Y", "openStatus": true}, {"minors": [], "sessionDates": null, "specialPermissionAddCode": null, "number": "05", "unitMajors": [], "subtitle": null, "specialPermissionDropCodeDescription": null, "specialPermissionAddCodeDescription": null, "subtopic": null, "majors": [], "index": "11128", "sectionNotes": "COMMON HOUR EXAM REQUIREDGO TO SCHEDULING.RUTGERS.EDUOPEN BY PLACEMENT EXAM ORPERMISSION OF DEPARTMENT.", "specialPermissionDropCode": null, "comments": [], "crossListedSections": [], "legendKey": null, "meetingTimes": [{"campusName": "COLLEGE AVENUE", "startTime": "0610", "meetingDay": "TH", "meetingModeDesc": "LEC", "roomNumber": "213", "campusLocation": "1", "buildingCode": "MU", "pmCode": "P", "baClassHours": null, "campusAbbrev": "CAC", "endTime": "0730", "meetingModeCode": "02"}, {"campusName": "COLLEGE AVENUE", "startTime": "0610", "meetingDay": "T", "meetingModeDesc": "LEC", "roomNumber": "213", "campusLocation": "1", "buildingCode": "MU", "pmCode": "P", "baClassHours": null, "campusAbbrev": "CAC", "endTime": "0730", "meetingModeCode": "02"}], "honorPrograms": [], "instructors": [], "printed": "Y", "examCode": "D", "campusCode": "NB", "sectionEligibility": null, "sessionDatePrintIndicator": "Y", "openStatus": true}, {"minors": [], "sessionDates": null, "specialPermissionAddCode": null, "number": "06", "unitMajors": [], "subtitle": null, "specialPermissionDropCodeDescription": null, "specialPermissionAddCodeDescription": null, "subtopic": null, "majors": [], "index": "07238", "sectionNotes": "COMMON HOUR EXAM REQUIREDGO TO SCHEDULING.RUTGERS.EDUOPEN BY PLACEMENT EXAM ORPERMISSION OF DEPT.", "specialPermissionDropCode": null, "comments": [], "crossListedSections": [], "legendKey": null, "meetingTimes": [{"campusName": "DOUGLAS/COOK", "startTime": "0215", "meetingDay": "TH", "meetingModeDesc": "LEC", "roomNumber": "216", "campusLocation": "4", "buildingCode": "HCK", "pmCode": "P", "baClassHours": null, "campusAbbrev": "D/C", "endTime": "0335", "meetingModeCode": "02"}, {"campusName": "DOUGLAS/COOK", "startTime": "0215", "meetingDay": "T", "meetingModeDesc": "LEC", "roomNumber": "216", "campusLocation": "4", "buildingCode": "HCK", "pmCode": "P", "baClassHours": null, "campusAbbrev": "D/C", "endTime": "0335", "meetingModeCode": "02"}], "honorPrograms": [], "instructors": [], "printed": "Y", "examCode": "D", "campusCode": "NB", "sectionEligibility": null, "sessionDatePrintIndicator": "Y", "openStatus": true}], "campusCode": "NB", "coreCodes": [], "courseNotes": "FOR ALL SECTIONS: PREREQ - PLACEMENT TEST OR PERMISSION OF DEPARTMENT \r\n", "title": "SPAN REVIEW & CONT", "supplementCode": "  ", "subjectGroupNotes": null, "courseDescription": null, "synopsisUrl": "http://span-port.rutgers.edu/course-synopses", "offeringUnitTitle": null, "openSections": 4, "credits": 3, "offeringUnitCode": "01", "preReqNotes": null, "unitNotes": null, "subjectNotes": "SEE PORTUGUESE(810) FOR ADDITIONAL COURSES. \r\n\r\nFOR ONLINE COURSES SELECT ONLINE COURSES UNDER COURSE TYPE TO SEE COURSE OFFERINGS.", "courseNumber": "121", "expandedTitle": "SPANISH REVIEW AND CONTINUATION                                                 ", "subject": "940"}, {"sections": [{"minors": [], "sessionDates": null, "specialPermissionAddCode": null, "number": "01", "unitMajors": [], "subtitle": null, "specialPermissionDropCodeDescription": null, "specialPermissionAddCodeDescription": null, "subtopic": null, "majors": [], "index": "02547", "sectionNotes": "COMMON HOUR EXAM REQUIREDGO TO SCHEDULING.RUTGERS.EDU", "specialPermissionDropCode": null, "comments": [], "crossListedSections": [], "legendKey": null, "meetingTimes": [{"campusName": "DOUGLAS/COOK", "startTime": "0355", "meetingDay": "TH", "meetingModeDesc": "LEC", "roomNumber": "110A", "campusLocation": "4", "buildingCode": "RAB", "pmCode": "P", "baClassHours": null, "campusAbbrev": "D/C", "endTime": "0545", "meetingModeCode": "02"}, {"campusName": "DOUGLAS/COOK", "startTime": "0355", "meetingDay": "T", "meetingModeDesc": "LEC", "roomNumber": "110A", "campusLocation": "4", "buildingCode": "RAB", "pmCode": "P", "baClassHours": null, "campusAbbrev": "D/C", "endTime": "0545", "meetingModeCode": "02"}], "honorPrograms": [], "instructors": [], "printed": "Y", "examCode": "D", "campusCode": "NB", "sectionEligibility": null, "sessionDatePrintIndicator": "Y", "openStatus": true}, {"minors": [], "sessionDates": null, "specialPermissionAddCode": null, "number": "02", "unitMajors": [], "subtitle": null, "specialPermissionDropCodeDescription": null, "specialPermissionAddCodeDescription": null, "subtopic": null, "majors": [], "index": "00454", "sectionNotes": "COMMON HOUR EXAM REQUIREDGO TO SCHEDULING.RUTGERS.EDU", "specialPermissionDropCode": null, "comments": [], "crossListedSections": [], "legendKey": null, "meetingTimes": [{"campusName": "COLLEGE AVENUE", "startTime": "0810", "meetingDay": "TH", "meetingModeDesc": "LEC", "roomNumber": "105", "campusLocation": "1", "buildingCode": "SC", "pmCode": "A", "baClassHours": null, "campusAbbrev": "CAC", "endTime": "0930", "meetingModeCode": "02"}, {"campusName": "COLLEGE AVENUE", "startTime": "0810", "meetingDay": "M", "meetingModeDesc": "LEC", "roomNumber": "105", "campusLocation": "1", "buildingCode": "SC", "pmCode": "A", "baClassHours": null, "campusAbbrev": "CAC", "endTime": "0930", "meetingModeCode": "02"}, {"campusName": "COLLEGE AVENUE", "startTime": "0810", "meetingDay": "W", "meetingModeDesc": "RECIT", "roomNumber": "105", "campusLocation": "1", "buildingCode": "SC", "pmCode": "A", "baClassHours": null, "campusAbbrev": "CAC", "endTime": "0930", "meetingModeCode": "03"}], "honorPrograms": [], "instructors": [], "printed": "Y", "examCode": "D", "campusCode": "NB", "sectionEligibility": null, "sessionDatePrintIndicator": "Y", "openStatus": true}, {"minors": [], "sessionDates": null, "specialPermissionAddCode": null, "number": "04", "unitMajors": [], "subtitle": null, "specialPermissionDropCodeDescription": null, "specialPermissionAddCodeDescription": null, "subtopic": null, "majors": [], "index": "00455", "sectionNotes": "COMMON HOUR EXAM REQUIREDGO TO SCHEDULING.RUTGERS.EDU", "specialPermissionDropCode": null, "comments": [], "crossListedSections": [], "legendKey": null, "meetingTimes": [{"campusName": "DOUGLAS/COOK", "startTime": "0215", "meetingDay": "W", "meetingModeDesc": "LEC", "roomNumber": "202", "campusLocation": "4", "buildingCode": "HCK", "pmCode": "P", "baClassHours": null, "campusAbbrev": "D/C", "endTime": "0405", "meetingModeCode": "02"}, {"campusName": "DOUGLAS/COOK", "startTime": "0215", "meetingDay": "M", "meetingModeDesc": "LEC", "roomNumber": "202", "campusLocation": "4", "buildingCode": "HCK", "pmCode": "P", "baClassHours": null, "campusAbbrev": "D/C", "endTime": "0405", "meetingModeCode": "02"}], "honorPrograms": [], "instructors": [], "printed": "Y", "examCode": "D", "campusCode": "NB", "sectionEligibility": null, "sessionDatePrintIndicator": "Y", "openStatus": true}, {"minors": [], "sessionDates": null, "specialPermissionAddCode": null, "number": "06", "unitMajors": [], "subtitle": null, "specialPermissionDropCodeDescription": null, "specialPermissionAddCodeDescription": null, "subtopic": null, "majors": [], "index": "08924", "sectionNotes": null, "specialPermissionDropCode": null, "comments": [{"code": "37", "description": "CHE sched at scheduling.rutgers.edu"}], "crossListedSections": [], "legendKey": null, "meetingTimes": [{"campusName": "COLLEGE AVENUE", "startTime": "0740", "meetingDay": "W", "meetingModeDesc": "LEC", "roomNumber": "2150", "campusLocation": "1", "buildingCode": "AB", "pmCode": "P", "baClassHours": null, "campusAbbrev": "CAC", "endTime": "0930", "meetingModeCode": "02"}, {"campusName": "COLLEGE AVENUE", "startTime": "0740", "meetingDay": "M", "meetingModeDesc": "LEC", "roomNumber": "2150", "campusLocation": "1", "buildingCode": "AB", "pmCode": "P", "baClassHours": null, "campusAbbrev": "CAC", "endTime": "0930", "meetingModeCode": "02"}], "honorPrograms": [], "instructors": [], "printed": "Y", "examCode": "D", "campusCode": "NB", "sectionEligibility": null, "sessionDatePrintIndicator": "Y", "openStatus": true}, {"minors": [], "sessionDates": null, "specialPermissionAddCode": null, "number": "90", "unitMajors": [], "subtitle": null, "specialPermissionDropCodeDescription": null, "specialPermissionAddCodeDescription": null, "subtopic": null, "majors": [], "index": "13600", "sectionNotes": null, "specialPermissionDropCode": null, "comments": [{"code": "61", "description": "$100 Online Course Support fee"}, {"code": "60", "description": "Go to http://Sakai.rutgers.edu"}, {"code": "56", "description": "Online Course"}], "crossListedSections": [], "legendKey": null, "meetingTimes": [{"campusName": null, "startTime": null, "meetingDay": null, "meetingModeDesc": "ONLINE INSTRUCTION(INTERNET)", "roomNumber": null, "campusLocation": null, "buildingCode": null, "pmCode": null, "baClassHours": "B", "campusAbbrev": null, "endTime": null, "meetingModeCode": "90"}], "honorPrograms": [], "instructors": [{"name": "MILLAN, M"}], "printed": "Y", "examCode": "A", "campusCode": "NB", "sectionEligibility": null, "sessionDatePrintIndicator": "Y", "openStatus": false}], "campusCode": "NB", "coreCodes": [], "courseNotes": "FOR ALL SECTIONS: PREREQ - 940:102 OR 121 OR PLACEMENT TEST \r\n", "title": "INTERMEDIATE SPANISH", "supplementCode": "  ", "subjectGroupNotes": null, "courseDescription": null, "synopsisUrl": "http://span-port.rutgers.edu/course-synopses", "offeringUnitTitle": null, "openSections": 4, "credits": 4, "offeringUnitCode": "01", "preReqNotes": "(01:940:102 )<em> OR </em>(01:940:121 )", "unitNotes": null, "subjectNotes": "SEE PORTUGUESE(810) FOR ADDITIONAL COURSES. \r\n\r\nFOR ONLINE COURSES SELECT ONLINE COURSES UNDER COURSE TYPE TO SEE COURSE OFFERINGS.", "courseNumber": "131", "expandedTitle": null, "subject": "940"}, {"sections": [{"minors": [], "sessionDates": null, "specialPermissionAddCode": null, "number": "02", "unitMajors": [], "subtitle": null, "specialPermissionDropCodeDescription": null, "specialPermissionAddCodeDescription": null, "subtopic": null, "majors": [], "index": "02549", "sectionNotes": "COMMON HOUR EXAM REQUIREDGO TO SCHEDULING.RUTGERS.EDU", "specialPermissionDropCode": null, "comments": [], "crossListedSections": [], "legendKey": null, "meetingTimes": [{"campusName": "COLLEGE AVENUE", "startTime": "0810", "meetingDay": "M", "meetingModeDesc": "LEC", "roomNumber": "101", "campusLocation": "1", "buildingCode": "SC", "pmCode": "A", "baClassHours": null, "campusAbbrev": "CAC", "endTime": "0930", "meetingModeCode": "02"}, {"campusName": "COLLEGE AVENUE", "startTime": "0810", "meetingDay": "TH", "meetingModeDesc": "LEC", "roomNumber": "101", "campusLocation": "1", "buildingCode": "SC", "pmCode": "A", "baClassHours": null, "campusAbbrev": "CAC", "endTime": "0930", "meetingModeCode": "02"}, {"campusName": "COLLEGE AVENUE", "startTime": "0810", "meetingDay": "T", "meetingModeDesc": "LEC", "roomNumber": "101", "campusLocation": "1", "buildingCode": "SC", "pmCode": "A", "baClassHours": null, "campusAbbrev": "CAC", "endTime": "0930", "meetingModeCode": "02"}], "honorPrograms": [], "instructors": [], "printed": "Y", "examCode": "D", "campusCode": "NB", "sectionEligibility": null, "sessionDatePrintIndicator": "Y", "openStatus": true}, {"minors": [], "sessionDates": null, "specialPermissionAddCode": null, "number": "03", "unitMajors": [], "subtitle": null, "specialPermissionDropCodeDescription": null, "specialPermissionAddCodeDescription": null, "subtopic": null, "majors": [], "index": "18755", "sectionNotes": null, "specialPermissionDropCode": null, "comments": [{"code": "37", "description": "CHE sched at scheduling.rutgers.edu"}], "crossListedSections": [], "legendKey": null, "meetingTimes": [{"campusName": "COLLEGE AVENUE", "startTime": "0740", "meetingDay": "T", "meetingModeDesc": "LEC", "roomNumber": "2250", "campusLocation": "1", "buildingCode": "AB", "pmCode": "P", "baClassHours": null, "campusAbbrev": "CAC", "endTime": "0930", "meetingModeCode": "02"}, {"campusName": "COLLEGE AVENUE", "startTime": "0740", "meetingDay": "TH", "meetingModeDesc": "LEC", "roomNumber": "2250", "campusLocation": "1", "buildingCode": "AB", "pmCode": "P", "baClassHours": null, "campusAbbrev": "CAC", "endTime": "0930", "meetingModeCode": "02"}], "honorPrograms": [], "instructors": [], "printed": "Y", "examCode": "D", "campusCode": "NB", "sectionEligibility": null, "sessionDatePrintIndicator": "Y", "openStatus": false}, {"minors": [], "sessionDates": null, "specialPermissionAddCode": null, "number": "90", "unitMajors": [], "subtitle": null, "specialPermissionDropCodeDescription": null, "specialPermissionAddCodeDescription": null, "subtopic": null, "majors": [], "index": "15370", "sectionNotes": null, "specialPermissionDropCode": null, "comments": [{"code": "61", "description": "$100 Online Course Support fee"}, {"code": "60", "description": "Go to http://Sakai.rutgers.edu"}, {"code": "56", "description": "Online Course"}], "crossListedSections": [], "legendKey": null, "meetingTimes": [{"campusName": null, "startTime": null, "meetingDay": null, "meetingModeDesc": "ONLINE INSTRUCTION(INTERNET)", "roomNumber": null, "campusLocation": null, "buildingCode": null, "pmCode": null, "baClassHours": "B", "campusAbbrev": null, "endTime": null, "meetingModeCode": "90"}], "honorPrograms": [], "instructors": [], "printed": "Y", "examCode": "A", "campusCode": "NB", "sectionEligibility": null, "sessionDatePrintIndicator": "Y", "openStatus": false}], "campusCode": "NB", "coreCodes": [{"code": "AHq", "description": "Nature of Languages", "effective": "20167", "course": "132", "supplement": null, "unit": "01", "subject": "940"}], "courseNotes": "FOR ALL SECTIONS: PREREQ - 940:131 OR PLACEMENT TEST OR PERMISSION OF DEPT. \r\n", "title": "INTERMEDIATE SPANISH", "supplementCode": "  ", "subjectGroupNotes": null, "courseDescription": null, "synopsisUrl": "http://span-port.rutgers.edu/course-synopses", "offeringUnitTitle": null, "openSections": 1, "credits": 4, "offeringUnitCode": "01", "preReqNotes": "(01:940:131 )", "unitNotes": null, "subjectNotes": "SEE PORTUGUESE(810) FOR ADDITIONAL COURSES. \r\n\r\nFOR ONLINE COURSES SELECT ONLINE COURSES UNDER COURSE TYPE TO SEE COURSE OFFERINGS.", "courseNumber": "132", "expandedTitle": null, "subject": "940"}, {"sections": [{"minors": [], "sessionDates": null, "specialPermissionAddCode": null, "number": "01", "unitMajors": [], "subtitle": null, "specialPermissionDropCodeDescription": null, "specialPermissionAddCodeDescription": null, "subtopic": null, "majors": [], "index": "06250", "sectionNotes": "PREREQ:PLACEMENT TEST ORPERMISSION OF DEPARTMENT", "specialPermissionDropCode": null, "comments": [], "crossListedSections": [], "legendKey": null, "meetingTimes": [{"campusName": "DOUGLAS/COOK", "startTime": "1235", "meetingDay": "TH", "meetingModeDesc": "LEC", "roomNumber": "104", "campusLocation": "4", "buildingCode": "RAB", "pmCode": "P", "baClassHours": null, "campusAbbrev": "D/C", "endTime": "0155", "meetingModeCode": "02"}, {"campusName": "DOUGLAS/COOK", "startTime": "1235", "meetingDay": "M", "meetingModeDesc": "LEC", "roomNumber": "104", "campusLocation": "4", "buildingCode": "RAB", "pmCode": "P", "baClassHours": null, "campusAbbrev": "D/C", "endTime": "0155", "meetingModeCode": "02"}], "honorPrograms": [], "instructors": [], "printed": "Y", "examCode": "C", "campusCode": "NB", "sectionEligibility": null, "sessionDatePrintIndicator": "Y", "openStatus": true}], "campusCode": "NB", "coreCodes": [], "courseNotes": null, "title": "SPAN NATIV SPKRS I", "supplementCode": "  ", "subjectGroupNotes": null, "courseDescription": null, "synopsisUrl": "http://span-port.rutgers.edu/course-synopses", "offeringUnitTitle": null, "openSections": 1, "credits": 3, "offeringUnitCode": "01", "preReqNotes": null, "unitNotes": null, "subjectNotes": "SEE PORTUGUESE(810) FOR ADDITIONAL COURSES. \r\n\r\nFOR ONLINE COURSES SELECT ONLINE COURSES UNDER COURSE TYPE TO SEE COURSE OFFERINGS.", "courseNumber": "139", "expandedTitle": "SPANISH FOR NATIVE SPEAKERS I                                                   ", "subject": "940"}, {"sections": [{"minors": [], "sessionDates": null, "specialPermissionAddCode": null, "number": "01", "unitMajors": [], "subtitle": null, "specialPermissionDropCodeDescription": null, "specialPermissionAddCodeDescription": null, "subtopic": null, "majors": [], "index": "08285", "sectionNotes": "PREREQ:  01:940:201 ORPERMISSION OF DEPT.  CREDIT NOTGIVEN FOR THIS COURSE & 940:204.", "specialPermissionDropCode": null, "comments": [], "crossListedSections": [], "legendKey": null, "meetingTimes": [{"campusName": "DOUGLAS/COOK", "startTime": "1235", "meetingDay": "TH", "meetingModeDesc": "LEC", "roomNumber": "214", "campusLocation": "4", "buildingCode": "HCK", "pmCode": "P", "baClassHours": null, "campusAbbrev": "D/C", "endTime": "0155", "meetingModeCode": "02"}, {"campusName": "DOUGLAS/COOK", "startTime": "1235", "meetingDay": "M", "meetingModeDesc": "LEC", "roomNumber": "214", "campusLocation": "4", "buildingCode": "HCK", "pmCode": "P", "baClassHours": null, "campusAbbrev": "D/C", "endTime": "0155", "meetingModeCode": "02"}], "honorPrograms": [], "instructors": [], "printed": "Y", "examCode": "C", "campusCode": "NB", "sectionEligibility": null, "sessionDatePrintIndicator": "Y", "openStatus": true}], "campusCode": "NB", "coreCodes": [], "courseNotes": null, "title": "CULT&COMP NATIVE SPK", "supplementCode": "  ", "subjectGroupNotes": null, "courseDescription": null, "synopsisUrl": "http://span-port.rutgers.edu/course-synopses", "offeringUnitTitle": null, "openSections": 1, "credits": 3, "offeringUnitCode": "01", "preReqNotes": "(01:940:201 )", "unitNotes": null, "subjectNotes": "SEE PORTUGUESE(810) FOR ADDITIONAL COURSES. \r\n\r\nFOR ONLINE COURSES SELECT ONLINE COURSES UNDER COURSE TYPE TO SEE COURSE OFFERINGS.", "courseNumber": "202", "expandedTitle": null, "subject": "940"}, {"sections": [{"minors": [], "sessionDates": null, "specialPermissionAddCode": null, "number": "01", "unitMajors": [], "subtitle": null, "specialPermissionDropCodeDescription": null, "specialPermissionAddCodeDescription": null, "subtopic": null, "majors": [], "index": "00456", "sectionNotes": null, "specialPermissionDropCode": null, "comments": [{"code": "35", "description": "See online schedule for prereqs"}], "crossListedSections": [], "legendKey": null, "meetingTimes": [{"campusName": "DOUGLAS/COOK", "startTime": "0215", "meetingDay": "T", "meetingModeDesc": "LEC", "roomNumber": "214", "campusLocation": "4", "buildingCode": "HCK", "pmCode": "P", "baClassHours": null, "campusAbbrev": "D/C", "endTime": "0335", "meetingModeCode": "02"}, {"campusName": "DOUGLAS/COOK", "startTime": "0215", "meetingDay": "TH", "meetingModeDesc": "LEC", "roomNumber": "214", "campusLocation": "4", "buildingCode": "HCK", "pmCode": "P", "baClassHours": null, "campusAbbrev": "D/C", "endTime": "0335", "meetingModeCode": "02"}], "honorPrograms": [], "instructors": [{"name": "BUTLER, B"}], "printed": "Y", "examCode": "O", "campusCode": "NB", "sectionEligibility": null, "sessionDatePrintIndicator": "Y", "openStatus": true}, {"minors": [], "sessionDates": null, "specialPermissionAddCode": null, "number": "02", "unitMajors": [], "subtitle": null, "specialPermissionDropCodeDescription": null, "specialPermissionAddCodeDescription": null, "subtopic": null, "majors": [], "index": "06133", "sectionNotes": null, "specialPermissionDropCode": null, "comments": [{"code": "35", "description": "See online schedule for prereqs"}], "crossListedSections": [], "legendKey": null, "meetingTimes": [{"campusName": "DOUGLAS/COOK", "startTime": "0355", "meetingDay": "T", "meetingModeDesc": "LEC", "roomNumber": "110B", "campusLocation": "4", "buildingCode": "RAB", "pmCode": "P", "baClassHours": null, "campusAbbrev": "D/C", "endTime": "0515", "meetingModeCode": "02"}, {"campusName": "DOUGLAS/COOK", "startTime": "0355", "meetingDay": "TH", "meetingModeDesc": "LEC", "roomNumber": "110B", "campusLocation": "4", "buildingCode": "RAB", "pmCode": "P", "baClassHours": null, "campusAbbrev": "D/C", "endTime": "0515", "meetingModeCode": "02"}], "honorPrograms": [], "instructors": [{"name": "BUTLER, B"}], "printed": "Y", "examCode": "O", "campusCode": "NB", "sectionEligibility": null, "sessionDatePrintIndicator": "Y", "openStatus": true}, {"minors": [], "sessionDates": null, "specialPermissionAddCode": null, "number": "03", "unitMajors": [], "subtitle": null, "specialPermissionDropCodeDescription": null, "specialPermissionAddCodeDescription": null, "subtopic": null, "majors": [], "index": "00457", "sectionNotes": null, "specialPermissionDropCode": null, "comments": [{"code": "35", "description": "See online schedule for prereqs"}], "crossListedSections": [], "legendKey": null, "meetingTimes": [{"campusName": "COLLEGE AVENUE", "startTime": "1130", "meetingDay": "TH", "meetingModeDesc": "LEC", "roomNumber": "105", "campusLocation": "1", "buildingCode": "SC", "pmCode": "A", "baClassHours": null, "campusAbbrev": "CAC", "endTime": "1250", "meetingModeCode": "02"}, {"campusName": "COLLEGE AVENUE", "startTime": "1130", "meetingDay": "M", "meetingModeDesc": "LEC", "roomNumber": "105", "campusLocation": "1", "buildingCode": "SC", "pmCode": "A", "baClassHours": null, "campusAbbrev": "CAC", "endTime": "1250", "meetingModeCode": "02"}], "honorPrograms": [], "instructors": [{"name": "NUNEZ, O"}], "printed": "Y", "examCode": "O", "campusCode": "NB", "sectionEligibility": null, "sessionDatePrintIndicator": "Y", "openStatus": true}, {"minors": [], "sessionDates": null, "specialPermissionAddCode": null, "number": "04", "unitMajors": [], "subtitle": null, "specialPermissionDropCodeDescription": null, "specialPermissionAddCodeDescription": null, "subtopic": null, "majors": [], "index": "05150", "sectionNotes": null, "specialPermissionDropCode": null, "comments": [{"code": "35", "description": "See online schedule for prereqs"}], "crossListedSections": [], "legendKey": null, "meetingTimes": [{"campusName": "COLLEGE AVENUE", "startTime": "0110", "meetingDay": "TH", "meetingModeDesc": "LEC", "roomNumber": "103", "campusLocation": "1", "buildingCode": "SC", "pmCode": "P", "baClassHours": null, "campusAbbrev": "CAC", "endTime": "0230", "meetingModeCode": "02"}, {"campusName": "COLLEGE AVENUE", "startTime": "0110", "meetingDay": "T", "meetingModeDesc": "LEC", "roomNumber": "103", "campusLocation": "1", "buildingCode": "SC", "pmCode": "P", "baClassHours": null, "campusAbbrev": "CAC", "endTime": "0230", "meetingModeCode": "02"}], "honorPrograms": [], "instructors": [{"name": "NUNEZ, O"}], "printed": "Y", "examCode": "O", "campusCode": "NB", "sectionEligibility": null, "sessionDatePrintIndicator": "Y", "openStatus": true}], "campusCode": "NB", "coreCodes": [], "courseNotes": "FOR ALL SECTIONS: PREREQ - 940:132, PLACEMENT TEST OR PERMISSION OF DEPARTMENT \r\n ", "title": "SPAN CONVERSATN&COMP", "supplementCode": "  ", "subjectGroupNotes": null, "courseDescription": null, "synopsisUrl": "http://span-port.rutgers.edu/course-synopses", "offeringUnitTitle": null, "openSections": 4, "credits": 3, "offeringUnitCode": "01", "preReqNotes": "(01:940:132 )", "unitNotes": null, "subjectNotes": "SEE PORTUGUESE(810) FOR ADDITIONAL COURSES. \r\n\r\nFOR ONLINE COURSES SELECT ONLINE COURSES UNDER COURSE TYPE TO SEE COURSE OFFERINGS.", "courseNumber": "203", "expandedTitle": null, "subject": "940"}, {"sections": [{"minors": [], "sessionDates": null, "specialPermissionAddCode": null, "number": "01", "unitMajors": [], "subtitle": null, "specialPermissionDropCodeDescription": null, "specialPermissionAddCodeDescription": null, "subtopic": null, "majors": [], "index": "05650", "sectionNotes": null, "specialPermissionDropCode": null, "comments": [], "crossListedSections": [], "legendKey": null, "meetingTimes": [{"campusName": "COLLEGE AVENUE", "startTime": "0250", "meetingDay": "T", "meetingModeDesc": "LEC", "roomNumber": "221", "campusLocation": "1", "buildingCode": "SC", "pmCode": "P", "baClassHours": null, "campusAbbrev": "CAC", "endTime": "0410", "meetingModeCode": "02"}, {"campusName": "COLLEGE AVENUE", "startTime": "0250", "meetingDay": "TH", "meetingModeDesc": "LEC", "roomNumber": "221", "campusLocation": "1", "buildingCode": "SC", "pmCode": "P", "baClassHours": null, "campusAbbrev": "CAC", "endTime": "0410", "meetingModeCode": "02"}], "honorPrograms": [], "instructors": [{"name": "SANCHEZ, K"}], "printed": "Y", "examCode": "O", "campusCode": "NB", "sectionEligibility": null, "sessionDatePrintIndicator": "Y", "openStatus": true}, {"minors": [], "sessionDates": null, "specialPermissionAddCode": null, "number": "02", "unitMajors": [], "subtitle": null, "specialPermissionDropCodeDescription": null, "specialPermissionAddCodeDescription": null, "subtopic": null, "majors": [], "index": "13601", "sectionNotes": null, "specialPermissionDropCode": null, "comments": [], "crossListedSections": [], "legendKey": null, "meetingTimes": [{"campusName": "COLLEGE AVENUE", "startTime": "0610", "meetingDay": "TH", "meetingModeDesc": "LEC", "roomNumber": "111", "campusLocation": "1", "buildingCode": "MU", "pmCode": "P", "baClassHours": null, "campusAbbrev": "CAC", "endTime": "0730", "meetingModeCode": "02"}, {"campusName": "COLLEGE AVENUE", "startTime": "0610", "meetingDay": "T", "meetingModeDesc": "LEC", "roomNumber": "111", "campusLocation": "1", "buildingCode": "MU", "pmCode": "P", "baClassHours": null, "campusAbbrev": "CAC", "endTime": "0730", "meetingModeCode": "02"}], "honorPrograms": [], "instructors": [{"name": "SANCHEZ, K"}], "printed": "Y", "examCode": "O", "campusCode": "NB", "sectionEligibility": null, "sessionDatePrintIndicator": "Y", "openStatus": true}, {"minors": [], "sessionDates": null, "specialPermissionAddCode": null, "number": "03", "unitMajors": [], "subtitle": null, "specialPermissionDropCodeDescription": null, "specialPermissionAddCodeDescription": null, "subtopic": null, "majors": [], "index": "13602", "sectionNotes": null, "specialPermissionDropCode": null, "comments": [], "crossListedSections": [], "legendKey": null, "meetingTimes": [{"campusName": "DOUGLAS/COOK", "startTime": "0715", "meetingDay": "M", "meetingModeDesc": "LEC", "roomNumber": "131", "campusLocation": "4", "buildingCode": "HCK", "pmCode": "P", "baClassHours": null, "campusAbbrev": "D/C", "endTime": "0835", "meetingModeCode": "02"}, {"campusName": "DOUGLAS/COOK", "startTime": "0715", "meetingDay": "W", "meetingModeDesc": "LEC", "roomNumber": "131", "campusLocation": "4", "buildingCode": "HCK", "pmCode": "P", "baClassHours": null, "campusAbbrev": "D/C", "endTime": "0835", "meetingModeCode": "02"}], "honorPrograms": [], "instructors": [{"name": "KIM, H"}], "printed": "Y", "examCode": "O", "campusCode": "NB", "sectionEligibility": null, "sessionDatePrintIndicator": "Y", "openStatus": true}], "campusCode": "NB", "coreCodes": [], "courseNotes": "FOR ALL SECTIONS: PREREQ OR COREQ - 940:203 OR PERM. OF DEPT. \r\nNOT OPEN TO NATIVE SPEAKERS OR OTHERS ALREADY      CONVERSANT IN LANGUAGE \r\n", "title": "CULTURE & COMPOSITN", "supplementCode": "  ", "subjectGroupNotes": null, "courseDescription": null, "synopsisUrl": "http://span-port.rutgers.edu/course-synopses", "offeringUnitTitle": null, "openSections": 3, "credits": 3, "offeringUnitCode": "01", "preReqNotes": "(01:940:203 )", "unitNotes": null, "subjectNotes": "SEE PORTUGUESE(810) FOR ADDITIONAL COURSES. \r\n\r\nFOR ONLINE COURSES SELECT ONLINE COURSES UNDER COURSE TYPE TO SEE COURSE OFFERINGS.", "courseNumber": "204", "expandedTitle": null, "subject": "940"}, {"sections": [{"minors": [], "sessionDates": null, "specialPermissionAddCode": null, "number": "02", "unitMajors": [], "subtitle": null, "specialPermissionDropCodeDescription": null, "specialPermissionAddCodeDescription": null, "subtopic": null, "majors": [], "index": "04767", "sectionNotes": null, "specialPermissionDropCode": null, "comments": [{"code": "35", "description": "See online schedule for prereqs"}], "crossListedSections": [], "legendKey": null, "meetingTimes": [{"campusName": "DOUGLAS/COOK", "startTime": "0355", "meetingDay": "T", "meetingModeDesc": "LEC", "roomNumber": "218", "campusLocation": "4", "buildingCode": "HCK", "pmCode": "P", "baClassHours": null, "campusAbbrev": "D/C", "endTime": "0515", "meetingModeCode": "02"}, {"campusName": "DOUGLAS/COOK", "startTime": "0355", "meetingDay": "TH", "meetingModeDesc": "LEC", "roomNumber": "218", "campusLocation": "4", "buildingCode": "HCK", "pmCode": "P", "baClassHours": null, "campusAbbrev": "D/C", "endTime": "0515", "meetingModeCode": "02"}], "honorPrograms": [], "instructors": [{"name": "KIM, YS"}], "printed": "Y", "examCode": "C", "campusCode": "NB", "sectionEligibility": null, "sessionDatePrintIndicator": "Y", "openStatus": true}, {"minors": [], "sessionDates": null, "specialPermissionAddCode": null, "number": "03", "unitMajors": [], "subtitle": null, "specialPermissionDropCodeDescription": null, "specialPermissionAddCodeDescription": null, "subtopic": null, "majors": [], "index": "04004", "sectionNotes": null, "specialPermissionDropCode": null, "comments": [{"code": "35", "description": "See online schedule for prereqs"}], "crossListedSections": [], "legendKey": null, "meetingTimes": [{"campusName": "DOUGLAS/COOK", "startTime": "0215", "meetingDay": "TH", "meetingModeDesc": "LEC", "roomNumber": "104", "campusLocation": "4", "buildingCode": "RAB", "pmCode": "P", "baClassHours": null, "campusAbbrev": "D/C", "endTime": "0335", "meetingModeCode": "02"}, {"campusName": "DOUGLAS/COOK", "startTime": "0215", "meetingDay": "T", "meetingModeDesc": "LEC", "roomNumber": "104", "campusLocation": "4", "buildingCode": "RAB", "pmCode": "P", "baClassHours": null, "campusAbbrev": "D/C", "endTime": "0335", "meetingModeCode": "02"}], "honorPrograms": [], "instructors": [{"name": "KIM, YS"}], "printed": "Y", "examCode": "O", "campusCode": "NB", "sectionEligibility": null, "sessionDatePrintIndicator": "Y", "openStatus": true}, {"minors": [], "sessionDates": null, "specialPermissionAddCode": null, "number": "04", "unitMajors": [], "subtitle": null, "specialPermissionDropCodeDescription": null, "specialPermissionAddCodeDescription": null, "subtopic": null, "majors": [], "index": "17356", "sectionNotes": null, "specialPermissionDropCode": null, "comments": [], "crossListedSections": [], "legendKey": null, "meetingTimes": [{"campusName": "DOUGLAS/COOK", "startTime": "1235", "meetingDay": "M", "meetingModeDesc": "LEC", "roomNumber": "106", "campusLocation": "4", "buildingCode": "HSB", "pmCode": "P", "baClassHours": null, "campusAbbrev": "D/C", "endTime": "0155", "meetingModeCode": "02"}, {"campusName": "DOUGLAS/COOK", "startTime": "1235", "meetingDay": "TH", "meetingModeDesc": "LEC", "roomNumber": "106", "campusLocation": "4", "buildingCode": "HSB", "pmCode": "P", "baClassHours": null, "campusAbbrev": "D/C", "endTime": "0155", "meetingModeCode": "02"}], "honorPrograms": [], "instructors": [{"name": "MARCONE, J"}], "printed": "Y", "examCode": "O", "campusCode": "NB", "sectionEligibility": null, "sessionDatePrintIndicator": "Y", "openStatus": true}, {"minors": [], "sessionDates": null, "specialPermissionAddCode": "03", "number": "H1", "unitMajors": [], "subtitle": null, "specialPermissionDropCodeDescription": null, "specialPermissionAddCodeDescription": "Department staff", "subtopic": null, "majors": [], "index": "09282", "sectionNotes": "PERMISSION OF DEPT.  HONORSSTUDENTS ONLY.", "specialPermissionDropCode": null, "comments": [{"code": "87", "description": "For Honors Students only"}], "crossListedSections": [], "legendKey": null, "meetingTimes": [{"campusName": "DOUGLAS/COOK", "startTime": "1055", "meetingDay": "TH", "meetingModeDesc": "LEC", "roomNumber": "110A", "campusLocation": "4", "buildingCode": "RAB", "pmCode": "A", "baClassHours": null, "campusAbbrev": "D/C", "endTime": "1215", "meetingModeCode": "02"}, {"campusName": "DOUGLAS/COOK", "startTime": "1055", "meetingDay": "M", "meetingModeDesc": "LEC", "roomNumber": "110A", "campusLocation": "4", "buildingCode": "RAB", "pmCode": "A", "baClassHours": null, "campusAbbrev": "D/C", "endTime": "1215", "meetingModeCode": "02"}], "honorPrograms": [{"code": "A"}], "instructors": [{"name": "BISHOP, K"}], "printed": "Y", "examCode": "C", "campusCode": "NB", "sectionEligibility": null, "sessionDatePrintIndicator": "Y", "openStatus": true}], "campusCode": "NB", "coreCodes": [{"code": "AHq", "description": "Nature of Languages", "effective": "20119", "course": "215", "supplement": null, "unit": "01", "subject": "940"}, {"code": "AHp", "description": "Arts and Literatures", "effective": "20119", "course": "215", "supplement": null, "unit": "01", "subject": "940"}], "courseNotes": null, "title": "INTRO HISPANIC LIT", "supplementCode": "  ", "subjectGroupNotes": null, "courseDescription": null, "synopsisUrl": "http://span-port.rutgers.edu/course-synopses", "offeringUnitTitle": null, "openSections": 4, "credits": 3, "offeringUnitCode": "01", "preReqNotes": "(01:940:202 CULT&COMP NATIVE SPK)<em> OR </em>(01:940:204 )", "unitNotes": null, "subjectNotes": "SEE PORTUGUESE(810) FOR ADDITIONAL COURSES. \r\n\r\nFOR ONLINE COURSES SELECT ONLINE COURSES UNDER COURSE TYPE TO SEE COURSE OFFERINGS.", "courseNumber": "215", "expandedTitle": null, "subject": "940"}, {"sections": [{"minors": [], "sessionDates": null, "specialPermissionAddCode": null, "number": "01", "unitMajors": [], "subtitle": null, "specialPermissionDropCodeDescription": null, "specialPermissionAddCodeDescription": null, "subtopic": null, "majors": [], "index": "08286", "sectionNotes": "CREDIT NOT GIVEN FOR THIS COURSEAND 615:101", "specialPermissionDropCode": null, "comments": [{"code": "23", "description": "Hybrid Section - Some Meetings Online"}, {"code": "60", "description": "Go to http://Sakai.rutgers.edu"}], "crossListedSections": [{"subjectCode": "615", "supplementCode": "  ", "registrationIndex": "05372", "offeringUnitCode": "01", "primaryRegistrationIndex": "08286", "courseNumber": "101", "offeringUnitCampus": "NB", "sectionNumber": "S1"}], "legendKey": null, "meetingTimes": [{"campusName": null, "startTime": null, "meetingDay": null, "meetingModeDesc": "HYBRID SECTION", "roomNumber": null, "campusLocation": null, "buildingCode": null, "pmCode": null, "baClassHours": "B", "campusAbbrev": null, "endTime": null, "meetingModeCode": "91"}, {"campusName": "DOUGLAS/COOK", "startTime": "1235", "meetingDay": "TH", "meetingModeDesc": "LEC", "roomNumber": "113", "campusLocation": "4", "buildingCode": "HCK", "pmCode": "P", "baClassHours": null, "campusAbbrev": "D/C", "endTime": "0155", "meetingModeCode": "02"}], "honorPrograms": [], "instructors": [], "printed": "Y", "examCode": "C", "campusCode": "NB", "sectionEligibility": null, "sessionDatePrintIndicator": "Y", "openStatus": true}, {"minors": [], "sessionDates": null, "specialPermissionAddCode": null, "number": "02", "unitMajors": [], "subtitle": null, "specialPermissionDropCodeDescription": null, "specialPermissionAddCodeDescription": null, "subtopic": null, "majors": [], "index": "11917", "sectionNotes": "CREDIT NOT GIVEN FOR THIS COURSEAND 615:101", "specialPermissionDropCode": null, "comments": [{"code": "60", "description": "Go to http://Sakai.rutgers.edu"}, {"code": "23", "description": "Hybrid Section - Some Meetings Online"}], "crossListedSections": [{"subjectCode": "615", "supplementCode": "  ", "registrationIndex": "12795", "offeringUnitCode": "01", "primaryRegistrationIndex": "11917", "courseNumber": "101", "offeringUnitCampus": "NB", "sectionNumber": "S2"}], "legendKey": null, "meetingTimes": [{"campusName": null, "startTime": null, "meetingDay": null, "meetingModeDesc": "HYBRID SECTION", "roomNumber": null, "campusLocation": null, "buildingCode": null, "pmCode": null, "baClassHours": "B", "campusAbbrev": null, "endTime": null, "meetingModeCode": "91"}, {"campusName": "DOUGLAS/COOK", "startTime": "0215", "meetingDay": "T", "meetingModeDesc": "LEC", "roomNumber": "110A", "campusLocation": "4", "buildingCode": "RAB", "pmCode": "P", "baClassHours": null, "campusAbbrev": "D/C", "endTime": "0335", "meetingModeCode": "02"}], "honorPrograms": [], "instructors": [], "printed": "Y", "examCode": "C", "campusCode": "NB", "sectionEligibility": null, "sessionDatePrintIndicator": "Y", "openStatus": true}], "campusCode": "NB", "coreCodes": [{"code": "AHq", "description": "Nature of Languages", "effective": "20119", "course": "261", "supplement": null, "unit": "01", "subject": "940"}], "courseNotes": "FOR ALL SECTIONS: PREREQ - 01:940:202 OR 01:940:204 OR PLACEMENT TEST. \r\nCREDIT NOT GIVEN FOR THIS COURSE & 615:101 \r\n", "title": "INTRO STUDY LANGUAGE", "supplementCode": "  ", "subjectGroupNotes": null, "courseDescription": null, "synopsisUrl": "http://span-port.rutgers.edu/course-synopses", "offeringUnitTitle": null, "openSections": 2, "credits": 3, "offeringUnitCode": "01", "preReqNotes": "(01:940:202 CULT&COMP NATIVE SPK)<em> OR </em>(01:940:204 )", "unitNotes": null, "subjectNotes": "SEE PORTUGUESE(810) FOR ADDITIONAL COURSES. \r\n\r\nFOR ONLINE COURSES SELECT ONLINE COURSES UNDER COURSE TYPE TO SEE COURSE OFFERINGS.", "courseNumber": "261", "expandedTitle": null, "subject": "940"}, {"sections": [{"minors": [], "sessionDates": null, "specialPermissionAddCode": null, "number": "01", "unitMajors": [], "subtitle": null, "specialPermissionDropCodeDescription": null, "specialPermissionAddCodeDescription": null, "subtopic": null, "majors": [], "index": "05869", "sectionNotes": null, "specialPermissionDropCode": null, "comments": [], "crossListedSections": [], "legendKey": null, "meetingTimes": [{"campusName": "DOUGLAS/COOK", "startTime": "1055", "meetingDay": "M", "meetingModeDesc": "LEC", "roomNumber": "213", "campusLocation": "4", "buildingCode": "HCK", "pmCode": "A", "baClassHours": null, "campusAbbrev": "D/C", "endTime": "1215", "meetingModeCode": "02"}, {"campusName": "DOUGLAS/COOK", "startTime": "1055", "meetingDay": "TH", "meetingModeDesc": "LEC", "roomNumber": "213", "campusLocation": "4", "buildingCode": "HCK", "pmCode": "A", "baClassHours": null, "campusAbbrev": "D/C", "endTime": "1215", "meetingModeCode": "02"}], "honorPrograms": [], "instructors": [{"name": "MARCONE, J"}], "printed": "Y", "examCode": "A", "campusCode": "NB", "sectionEligibility": null, "sessionDatePrintIndicator": "Y", "openStatus": false}, {"minors": [], "sessionDates": null, "specialPermissionAddCode": null, "number": "02", "unitMajors": [], "subtitle": null, "specialPermissionDropCodeDescription": null, "specialPermissionAddCodeDescription": null, "subtopic": null, "majors": [], "index": "18918", "sectionNotes": null, "specialPermissionDropCode": null, "comments": [], "crossListedSections": [], "legendKey": null, "meetingTimes": [{"campusName": "DOUGLAS/COOK", "startTime": "0215", "meetingDay": "M", "meetingModeDesc": "LEC", "roomNumber": "115", "campusLocation": "4", "buildingCode": "HCK", "pmCode": "P", "baClassHours": null, "campusAbbrev": "D/C", "endTime": "0335", "meetingModeCode": "02"}, {"campusName": "DOUGLAS/COOK", "startTime": "0215", "meetingDay": "W", "meetingModeDesc": "LEC", "roomNumber": "115", "campusLocation": "4", "buildingCode": "HCK", "pmCode": "P", "baClassHours": null, "campusAbbrev": "D/C", "endTime": "0335", "meetingModeCode": "02"}], "honorPrograms": [], "instructors": [], "printed": "Y", "examCode": "O", "campusCode": "NB", "sectionEligibility": null, "sessionDatePrintIndicator": "Y", "openStatus": false}], "campusCode": "NB", "coreCodes": [], "courseNotes": null, "title": "ADV SPAN CONVERSATN", "supplementCode": "  ", "subjectGroupNotes": null, "courseDescription": null, "synopsisUrl": "http://span-port.rutgers.edu/course-synopses", "offeringUnitTitle": null, "openSections": 0, "credits": 3, "offeringUnitCode": "01", "preReqNotes": "(01:940:215 )<em> OR </em>(01:940:261 )<em> OR </em>(01:940:325 )", "unitNotes": null, "subjectNotes": "SEE PORTUGUESE(810) FOR ADDITIONAL COURSES. \r\n\r\nFOR ONLINE COURSES SELECT ONLINE COURSES UNDER COURSE TYPE TO SEE COURSE OFFERINGS.", "courseNumber": "313", "expandedTitle": "ADVANCED SPANISH CONVERSATION AND CONTEMPORARY ISSUES                           ", "subject": "940"}, {"sections": [{"minors": [], "sessionDates": null, "specialPermissionAddCode": null, "number": "01", "unitMajors": [], "subtitle": null, "specialPermissionDropCodeDescription": null, "specialPermissionAddCodeDescription": null, "subtopic": null, "majors": [], "index": "03016", "sectionNotes": "PREREQS: 01:940:202 OR 204", "specialPermissionDropCode": null, "comments": [], "crossListedSections": [], "legendKey": null, "meetingTimes": [{"campusName": "DOUGLAS/COOK", "startTime": "0215", "meetingDay": "M", "meetingModeDesc": "LEC", "roomNumber": "207", "campusLocation": "4", "buildingCode": "RAB", "pmCode": "P", "baClassHours": null, "campusAbbrev": "D/C", "endTime": "0335", "meetingModeCode": "02"}, {"campusName": "DOUGLAS/COOK", "startTime": "0215", "meetingDay": "W", "meetingModeDesc": "LEC", "roomNumber": "207", "campusLocation": "4", "buildingCode": "RAB", "pmCode": "P", "baClassHours": null, "campusAbbrev": "D/C", "endTime": "0335", "meetingModeCode": "02"}], "honorPrograms": [], "instructors": [{"name": "KIM, H."}], "printed": "Y", "examCode": "C", "campusCode": "NB", "sectionEligibility": null, "sessionDatePrintIndicator": "Y", "openStatus": true}, {"minors": [], "sessionDates": null, "specialPermissionAddCode": null, "number": "03", "unitMajors": [], "subtitle": null, "specialPermissionDropCodeDescription": null, "specialPermissionAddCodeDescription": null, "subtopic": null, "majors": [], "index": "03618", "sectionNotes": "PREREQS: 01:940:202 OR 204OR PLACEMENT TEST", "specialPermissionDropCode": null, "comments": [], "crossListedSections": [], "legendKey": null, "meetingTimes": [{"campusName": "DOUGLAS/COOK", "startTime": "0355", "meetingDay": "M", "meetingModeDesc": "LEC", "roomNumber": "122", "campusLocation": "4", "buildingCode": "HCK", "pmCode": "P", "baClassHours": null, "campusAbbrev": "D/C", "endTime": "0515", "meetingModeCode": "02"}, {"campusName": "DOUGLAS/COOK", "startTime": "0355", "meetingDay": "W", "meetingModeDesc": "LEC", "roomNumber": "122", "campusLocation": "4", "buildingCode": "HCK", "pmCode": "P", "baClassHours": null, "campusAbbrev": "D/C", "endTime": "0515", "meetingModeCode": "02"}], "honorPrograms": [], "instructors": [{"name": "KIM, H"}], "printed": "Y", "examCode": "C", "campusCode": "NB", "sectionEligibility": null, "sessionDatePrintIndicator": "Y", "openStatus": true}, {"minors": [], "sessionDates": null, "specialPermissionAddCode": null, "number": "04", "unitMajors": [], "subtitle": null, "specialPermissionDropCodeDescription": null, "specialPermissionAddCodeDescription": null, "subtopic": null, "majors": [], "index": "18757", "sectionNotes": null, "specialPermissionDropCode": null, "comments": [], "crossListedSections": [], "legendKey": null, "meetingTimes": [{"campusName": "COLLEGE AVENUE", "startTime": "0740", "meetingDay": "TH", "meetingModeDesc": "LEC", "roomNumber": "2150", "campusLocation": "1", "buildingCode": "AB", "pmCode": "P", "baClassHours": null, "campusAbbrev": "CAC", "endTime": "0900", "meetingModeCode": "02"}, {"campusName": "COLLEGE AVENUE", "startTime": "0740", "meetingDay": "T", "meetingModeDesc": "LEC", "roomNumber": "2150", "campusLocation": "1", "buildingCode": "AB", "pmCode": "P", "baClassHours": null, "campusAbbrev": "CAC", "endTime": "0900", "meetingModeCode": "02"}], "honorPrograms": [], "instructors": [], "printed": "Y", "examCode": "C", "campusCode": "NB", "sectionEligibility": null, "sessionDatePrintIndicator": "Y", "openStatus": true}], "campusCode": "NB", "coreCodes": [], "courseNotes": "FOR ALL SECTIONS: PREREQ - 01:940:202 OR 204 OR PLACEMENT TEST \r\n ", "title": "ADV GRAMMAR&COMPOSTN", "supplementCode": "  ", "subjectGroupNotes": null, "courseDescription": null, "synopsisUrl": "http://span-port.rutgers.edu/course-synopses", "offeringUnitTitle": null, "openSections": 3, "credits": 3, "offeringUnitCode": "01", "preReqNotes": "(01:940:202 CULT&COMP NATIVE SPK)<em> OR </em>(01:940:204 )", "unitNotes": null, "subjectNotes": "SEE PORTUGUESE(810) FOR ADDITIONAL COURSES. \r\n\r\nFOR ONLINE COURSES SELECT ONLINE COURSES UNDER COURSE TYPE TO SEE COURSE OFFERINGS.", "courseNumber": "325", "expandedTitle": "ADVANCED GRAMMAR AND COMPOSITION                                                ", "subject": "940"}, {"sections": [{"minors": [], "sessionDates": null, "specialPermissionAddCode": null, "number": "01", "unitMajors": [], "subtitle": null, "specialPermissionDropCodeDescription": null, "specialPermissionAddCodeDescription": null, "subtopic": null, "majors": [], "index": "02552", "sectionNotes": null, "specialPermissionDropCode": null, "comments": [{"code": "35", "description": "See online schedule for prereqs"}, {"code": "23", "description": "Hybrid Section - Some Meetings Online"}, {"code": "60", "description": "Go to http://Sakai.rutgers.edu"}], "crossListedSections": [], "legendKey": null, "meetingTimes": [{"campusName": "COLLEGE AVENUE", "startTime": "0610", "meetingDay": "T", "meetingModeDesc": "LEC", "roomNumber": "A4", "campusLocation": "1", "buildingCode": "FH", "pmCode": "P", "baClassHours": null, "campusAbbrev": "CAC", "endTime": "0730", "meetingModeCode": "02"}, {"campusName": null, "startTime": null, "meetingDay": null, "meetingModeDesc": "HYBRID SECTION", "roomNumber": null, "campusLocation": null, "buildingCode": null, "pmCode": null, "baClassHours": "B", "campusAbbrev": null, "endTime": null, "meetingModeCode": "91"}], "honorPrograms": [], "instructors": [], "printed": "Y", "examCode": "C", "campusCode": "NB", "sectionEligibility": null, "sessionDatePrintIndicator": "Y", "openStatus": true}], "campusCode": "NB", "coreCodes": [], "courseNotes": null, "title": "ADV COMP&INT TRANLAT", "supplementCode": "  ", "subjectGroupNotes": null, "courseDescription": null, "synopsisUrl": "http://span-port.rutgers.edu/course-synopses", "offeringUnitTitle": null, "openSections": 1, "credits": 3, "offeringUnitCode": "01", "preReqNotes": "(01:940:325 )", "unitNotes": null, "subjectNotes": "SEE PORTUGUESE(810) FOR ADDITIONAL COURSES. \r\n\r\nFOR ONLINE COURSES SELECT ONLINE COURSES UNDER COURSE TYPE TO SEE COURSE OFFERINGS.", "courseNumber": "326", "expandedTitle": null, "subject": "940"}, {"sections": [{"minors": [], "sessionDates": null, "specialPermissionAddCode": null, "number": "01", "unitMajors": [], "subtitle": null, "specialPermissionDropCodeDescription": null, "specialPermissionAddCodeDescription": null, "subtopic": null, "majors": [], "index": "07042", "sectionNotes": null, "specialPermissionDropCode": null, "comments": [{"code": "35", "description": "See online schedule for prereqs"}], "crossListedSections": [], "legendKey": null, "meetingTimes": [{"campusName": "DOUGLAS/COOK", "startTime": "1055", "meetingDay": "TH", "meetingModeDesc": "LEC", "roomNumber": "207", "campusLocation": "4", "buildingCode": "RAB", "pmCode": "A", "baClassHours": null, "campusAbbrev": "D/C", "endTime": "0155", "meetingModeCode": "02"}], "honorPrograms": [], "instructors": [{"name": "NARVAEZ, C"}], "printed": "Y", "examCode": "O", "campusCode": "NB", "sectionEligibility": null, "sessionDatePrintIndicator": "Y", "openStatus": false}], "campusCode": "NB", "coreCodes": [], "courseNotes": null, "title": "LIT&CULT HISP CARIBB", "supplementCode": "  ", "subjectGroupNotes": null, "courseDescription": null, "synopsisUrl": "http://span-port.rutgers.edu/course-synopses", "offeringUnitTitle": null, "openSections": 0, "credits": 3, "offeringUnitCode": "01", "preReqNotes": "(01:940:215 )<em> OR </em>(01:940:217 INTRO HISP LIT HONOR)<em> OR </em>(01:940:332 LIT&CULT HISP CARIBB)<em> OR </em>(01:940:333 )<em> OR </em>(01:940:334 MOD IDENT SPAN AMER)<em> OR </em>(01:940:335 LIT&CULT OF SPAIN)<em> OR </em>(01:940:336 LIT&CULT OF SPAIN)", "unitNotes": null, "subjectNotes": "SEE PORTUGUESE(810) FOR ADDITIONAL COURSES. \r\n\r\nFOR ONLINE COURSES SELECT ONLINE COURSES UNDER COURSE TYPE TO SEE COURSE OFFERINGS.", "courseNumber": "331", "expandedTitle": "LITERATURE AND CULTURE OF THE HISPANIC CARIBBEAN                                ", "subject": "940"}, {"sections": [{"minors": [], "sessionDates": null, "specialPermissionAddCode": null, "number": "01", "unitMajors": [], "subtitle": null, "specialPermissionDropCodeDescription": null, "specialPermissionAddCodeDescription": null, "subtopic": null, "majors": [], "index": "18758", "sectionNotes": null, "specialPermissionDropCode": null, "comments": [], "crossListedSections": [], "legendKey": null, "meetingTimes": [{"campusName": "COLLEGE AVENUE", "startTime": "0950", "meetingDay": "TH", "meetingModeDesc": "LEC", "roomNumber": "111", "campusLocation": "1", "buildingCode": "MU", "pmCode": "A", "baClassHours": null, "campusAbbrev": "CAC", "endTime": "1110", "meetingModeCode": "02"}, {"campusName": "COLLEGE AVENUE", "startTime": "0950", "meetingDay": "M", "meetingModeDesc": "LEC", "roomNumber": "111", "campusLocation": "1", "buildingCode": "MU", "pmCode": "A", "baClassHours": null, "campusAbbrev": "CAC", "endTime": "1110", "meetingModeCode": "02"}], "honorPrograms": [], "instructors": [{"name": "OTERO-TORRES"}], "printed": "Y", "examCode": "C", "campusCode": "NB", "sectionEligibility": null, "sessionDatePrintIndicator": "Y", "openStatus": true}], "campusCode": "NB", "coreCodes": [], "courseNotes": null, "title": "LIT&CULT OF SPAIN", "supplementCode": "  ", "subjectGroupNotes": null, "courseDescription": null, "synopsisUrl": "http://span-port.rutgers.edu/course-synopses", "offeringUnitTitle": null, "openSections": 1, "credits": 3, "offeringUnitCode": "01", "preReqNotes": "(01:940:215 )<em> OR </em>(01:940:217 INTRO HISP LIT HONOR)<em> OR </em>(01:940:331 LIT&CULT HISP CARIBB)<em> OR </em>(01:940:332 LIT&CULT HISP CARIBB)<em> OR </em>(01:940:333 )<em> OR </em>(01:940:334 MOD IDENT SPAN AMER)<em> OR </em>(01:940:336 LIT&CULT OF SPAIN)", "unitNotes": null, "subjectNotes": "SEE PORTUGUESE(810) FOR ADDITIONAL COURSES. \r\n\r\nFOR ONLINE COURSES SELECT ONLINE COURSES UNDER COURSE TYPE TO SEE COURSE OFFERINGS.", "courseNumber": "335", "expandedTitle": "LITERATURE AND CULTURE OF SPAIN                                                 ", "subject": "940"}, {"sections": [{"minors": [], "sessionDates": null, "specialPermissionAddCode": null, "number": "01", "unitMajors": [], "subtitle": null, "specialPermissionDropCodeDescription": null, "specialPermissionAddCodeDescription": null, "subtopic": null, "majors": [], "index": "18759", "sectionNotes": "WILL COUNT FOR 940 MAJOR/MINORIF ALL WRITTEN WORK DONE INSPANISH.", "specialPermissionDropCode": null, "comments": [{"code": "20", "description": "Taught in English"}], "crossListedSections": [{"subjectCode": "988", "supplementCode": "  ", "registrationIndex": "19148", "offeringUnitCode": "01", "primaryRegistrationIndex": "18759", "courseNumber": "351", "offeringUnitCampus": "NB", "sectionNumber": "01"}], "legendKey": null, "meetingTimes": [{"campusName": "DOUGLAS/COOK", "startTime": "0535", "meetingDay": "T", "meetingModeDesc": "LEC", "roomNumber": "213", "campusLocation": "4", "buildingCode": "HCK", "pmCode": "P", "baClassHours": null, "campusAbbrev": "D/C", "endTime": "0655", "meetingModeCode": "02"}, {"campusName": "DOUGLAS/COOK", "startTime": "0535", "meetingDay": "TH", "meetingModeDesc": "LEC", "roomNumber": "213", "campusLocation": "4", "buildingCode": "HCK", "pmCode": "P", "baClassHours": null, "campusAbbrev": "D/C", "endTime": "0655", "meetingModeCode": "02"}], "honorPrograms": [], "instructors": [{"name": "BUTLER, B"}], "printed": "Y", "examCode": "C", "campusCode": "NB", "sectionEligibility": null, "sessionDatePrintIndicator": "Y", "openStatus": false}], "campusCode": "NB", "coreCodes": [{"code": "AHp", "description": "Arts and Literatures", "effective": "20169", "course": "351", "supplement": null, "unit": "01", "subject": "940"}], "courseNotes": null, "title": "WOM WRT HSP WLD ENGL", "supplementCode": "  ", "subjectGroupNotes": null, "courseDescription": null, "synopsisUrl": "http://span-port.rutgers.edu/course-synopses", "offeringUnitTitle": null, "openSections": 0, "credits": 3, "offeringUnitCode": "01", "preReqNotes": null, "unitNotes": null, "subjectNotes": "SEE PORTUGUESE(810) FOR ADDITIONAL COURSES. \r\n\r\nFOR ONLINE COURSES SELECT ONLINE COURSES UNDER COURSE TYPE TO SEE COURSE OFFERINGS.", "courseNumber": "351", "expandedTitle": null, "subject": "940"}, {"sections": [{"minors": [], "sessionDates": null, "specialPermissionAddCode": null, "number": "01", "unitMajors": [], "subtitle": null, "specialPermissionDropCodeDescription": null, "specialPermissionAddCodeDescription": null, "subtopic": null, "majors": [], "index": "05868", "sectionNotes": "PREREQ: 01:940:325 OR EQUIVALENTOR PERMISSION OF DEPARTMENT", "specialPermissionDropCode": null, "comments": [], "crossListedSections": [], "legendKey": null, "meetingTimes": [{"campusName": "COLLEGE AVENUE", "startTime": "0610", "meetingDay": "T", "meetingModeDesc": "LEC", "roomNumber": "104", "campusLocation": "1", "buildingCode": "LLB", "pmCode": "P", "baClassHours": null, "campusAbbrev": "CAC", "endTime": "0900", "meetingModeCode": "02"}], "honorPrograms": [], "instructors": [], "printed": "Y", "examCode": "S", "campusCode": "NB", "sectionEligibility": null, "sessionDatePrintIndicator": "Y", "openStatus": true}], "campusCode": "NB", "coreCodes": [], "courseNotes": null, "title": "SPANISH FOR COMMERCE", "supplementCode": "  ", "subjectGroupNotes": null, "courseDescription": null, "synopsisUrl": "http://span-port.rutgers.edu/course-synopses", "offeringUnitTitle": null, "openSections": 1, "credits": 3, "offeringUnitCode": "01", "preReqNotes": "(01:940:325 )", "unitNotes": null, "subjectNotes": "SEE PORTUGUESE(810) FOR ADDITIONAL COURSES. \r\n\r\nFOR ONLINE COURSES SELECT ONLINE COURSES UNDER COURSE TYPE TO SEE COURSE OFFERINGS.", "courseNumber": "360", "expandedTitle": null, "subject": "940"}, {"sections": [{"minors": [], "sessionDates": null, "specialPermissionAddCode": null, "number": "01", "unitMajors": [], "subtitle": null, "specialPermissionDropCodeDescription": null, "specialPermissionAddCodeDescription": null, "subtopic": null, "majors": [], "index": "11234", "sectionNotes": null, "specialPermissionDropCode": null, "comments": [], "crossListedSections": [], "legendKey": null, "meetingTimes": [{"campusName": "DOUGLAS/COOK", "startTime": "0915", "meetingDay": "M", "meetingModeDesc": "LEC", "roomNumber": "210", "campusLocation": "4", "buildingCode": "HCK", "pmCode": "A", "baClassHours": null, "campusAbbrev": "D/C", "endTime": "1035", "meetingModeCode": "02"}, {"campusName": "DOUGLAS/COOK", "startTime": "0915", "meetingDay": "TH", "meetingModeDesc": "LEC", "roomNumber": "210", "campusLocation": "4", "buildingCode": "HCK", "pmCode": "A", "baClassHours": null, "campusAbbrev": "D/C", "endTime": "1035", "meetingModeCode": "02"}], "honorPrograms": [], "instructors": [], "printed": "Y", "examCode": "C", "campusCode": "NB", "sectionEligibility": null, "sessionDatePrintIndicator": "Y", "openStatus": true}], "campusCode": "NB", "coreCodes": [], "courseNotes": null, "title": "SPAN PHONETCS&PHONOL", "supplementCode": "  ", "subjectGroupNotes": null, "courseDescription": null, "synopsisUrl": "http://span-port.rutgers.edu/course-synopses", "offeringUnitTitle": null, "openSections": 1, "credits": 3, "offeringUnitCode": "01", "preReqNotes": "(01:940:261 )", "unitNotes": null, "subjectNotes": "SEE PORTUGUESE(810) FOR ADDITIONAL COURSES. \r\n\r\nFOR ONLINE COURSES SELECT ONLINE COURSES UNDER COURSE TYPE TO SEE COURSE OFFERINGS.", "courseNumber": "362", "expandedTitle": "SPANISH PHONETICS AND PHONOLOGY                                                 ", "subject": "940"}, {"sections": [{"minors": [], "sessionDates": null, "specialPermissionAddCode": null, "number": "01", "unitMajors": [], "subtitle": null, "specialPermissionDropCodeDescription": null, "specialPermissionAddCodeDescription": null, "subtopic": null, "majors": [], "index": "19453", "sectionNotes": "PREREQ:  940:261 OR EQUIVALENT.", "specialPermissionDropCode": null, "comments": [], "crossListedSections": [], "legendKey": null, "meetingTimes": [{"campusName": "COLLEGE AVENUE", "startTime": "0430", "meetingDay": "T", "meetingModeDesc": "LEC", "roomNumber": "110", "campusLocation": "1", "buildingCode": "LLB", "pmCode": "P", "baClassHours": null, "campusAbbrev": "CAC", "endTime": "0730", "meetingModeCode": "02"}], "honorPrograms": [], "instructors": [{"name": "STEPHENS, T"}], "printed": "Y", "examCode": "C", "campusCode": "NB", "sectionEligibility": null, "sessionDatePrintIndicator": "Y", "openStatus": true}], "campusCode": "NB", "coreCodes": [], "courseNotes": null, "title": "SOCIOLNG SPAN SPK WL", "supplementCode": "  ", "subjectGroupNotes": null, "courseDescription": null, "synopsisUrl": "http://span-port.rutgers.edu/course-synopses", "offeringUnitTitle": null, "openSections": 1, "credits": 3, "offeringUnitCode": "01", "preReqNotes": null, "unitNotes": null, "subjectNotes": "SEE PORTUGUESE(810) FOR ADDITIONAL COURSES. \r\n\r\nFOR ONLINE COURSES SELECT ONLINE COURSES UNDER COURSE TYPE TO SEE COURSE OFFERINGS.", "courseNumber": "367", "expandedTitle": null, "subject": "940"}, {"sections": [{"minors": [], "sessionDates": null, "specialPermissionAddCode": null, "number": "90", "unitMajors": [], "subtitle": null, "specialPermissionDropCodeDescription": null, "specialPermissionAddCodeDescription": null, "subtopic": null, "majors": [], "index": "18820", "sectionNotes": "9/6-10/18  OPEN TO JUNIORS AND& SENIORS MAJORING OR MINORINGIN SPANISH.  BOTH NATIVE &NON-NATIVE SPANISH SPEAKERS.", "specialPermissionDropCode": null, "comments": [{"code": "62", "description": "$60 Online Course Support fee"}, {"code": "56", "description": "Online Course"}, {"code": "60", "description": "Go to http://Sakai.rutgers.edu"}, {"code": "12", "description": "First 7 weeks"}], "crossListedSections": [], "legendKey": null, "meetingTimes": [{"campusName": null, "startTime": null, "meetingDay": null, "meetingModeDesc": "ONLINE INSTRUCTION(INTERNET)", "roomNumber": null, "campusLocation": null, "buildingCode": null, "pmCode": null, "baClassHours": "B", "campusAbbrev": null, "endTime": null, "meetingModeCode": "90"}], "honorPrograms": [], "instructors": [{"name": "VILLALBA, C"}], "printed": "Y", "examCode": "A", "campusCode": "NB", "sectionEligibility": "JUNIORS AND SENIORS ", "sessionDatePrintIndicator": "Y", "openStatus": false}], "campusCode": "NB", "coreCodes": [], "courseNotes": null, "title": "SPAN LAB ORAL PROF I", "supplementCode": "  ", "subjectGroupNotes": null, "courseDescription": null, "synopsisUrl": "http://span-port.rutgers.edu/course-synopses", "offeringUnitTitle": null, "openSections": 0, "credits": 1, "offeringUnitCode": "01", "preReqNotes": null, "unitNotes": null, "subjectNotes": "SEE PORTUGUESE(810) FOR ADDITIONAL COURSES. \r\n\r\nFOR ONLINE COURSES SELECT ONLINE COURSES UNDER COURSE TYPE TO SEE COURSE OFFERINGS.", "courseNumber": "389", "expandedTitle": "SPANISH LAB FOR ORAL PROFICIENCY                                                ", "subject": "940"}, {"sections": [{"minors": [], "sessionDates": null, "specialPermissionAddCode": null, "number": "90", "unitMajors": [], "subtitle": null, "specialPermissionDropCodeDescription": null, "specialPermissionAddCodeDescription": null, "subtopic": null, "majors": [], "index": "15379", "sectionNotes": null, "specialPermissionDropCode": null, "comments": [{"code": "60", "description": "Go to http://Sakai.rutgers.edu"}, {"code": "61", "description": "$100 Online Course Support fee"}, {"code": "56", "description": "Online Course"}], "crossListedSections": [], "legendKey": null, "meetingTimes": [{"campusName": null, "startTime": null, "meetingDay": null, "meetingModeDesc": "ONLINE INSTRUCTION(INTERNET)", "roomNumber": null, "campusLocation": null, "buildingCode": null, "pmCode": null, "baClassHours": "B", "campusAbbrev": null, "endTime": null, "meetingModeCode": "90"}], "honorPrograms": [], "instructors": [], "printed": "Y", "examCode": "A", "campusCode": "NB", "sectionEligibility": "JUNIORS AND SENIORS ", "sessionDatePrintIndicator": "Y", "openStatus": true}], "campusCode": "NB", "coreCodes": [], "courseNotes": null, "title": "ADV TRANSLATION I", "supplementCode": "  ", "subjectGroupNotes": null, "courseDescription": null, "synopsisUrl": "http://span-port.rutgers.edu/course-synopses", "offeringUnitTitle": null, "openSections": 1, "credits": 3, "offeringUnitCode": "01", "preReqNotes": "(01:940:325 )<em> AND </em>(01:940:326 )<em> AND </em>(01:355:101 )", "unitNotes": null, "subjectNotes": "SEE PORTUGUESE(810) FOR ADDITIONAL COURSES. \r\n\r\nFOR ONLINE COURSES SELECT ONLINE COURSES UNDER COURSE TYPE TO SEE COURSE OFFERINGS.", "courseNumber": "401", "expandedTitle": "ADVANCED TRANSLATION I                                                          ", "subject": "940"}, {"sections": [{"minors": [], "sessionDates": null, "specialPermissionAddCode": null, "number": "90", "unitMajors": [], "subtitle": null, "specialPermissionDropCodeDescription": null, "specialPermissionAddCodeDescription": null, "subtopic": null, "majors": [], "index": "18761", "sectionNotes": null, "specialPermissionDropCode": null, "comments": [{"code": "56", "description": "Online Course"}, {"code": "60", "description": "Go to http://Sakai.rutgers.edu"}, {"code": "61", "description": "$100 Online Course Support fee"}], "crossListedSections": [{"subjectCode": "940", "supplementCode": "  ", "registrationIndex": "18765", "offeringUnitCode": "16", "primaryRegistrationIndex": "18761", "courseNumber": "506", "offeringUnitCampus": "NB", "sectionNumber": "90"}], "legendKey": null, "meetingTimes": [{"campusName": null, "startTime": null, "meetingDay": null, "meetingModeDesc": "ONLINE INSTRUCTION(INTERNET)", "roomNumber": null, "campusLocation": null, "buildingCode": null, "pmCode": null, "baClassHours": "B", "campusAbbrev": null, "endTime": null, "meetingModeCode": "90"}], "honorPrograms": [], "instructors": [{"name": "SANCHEZ, K"}], "printed": "Y", "examCode": "A", "campusCode": "NB", "sectionEligibility": null, "sessionDatePrintIndicator": "Y", "openStatus": false}], "campusCode": "NB", "coreCodes": [], "courseNotes": null, "title": "CIVILIZATN OF SP-AM", "supplementCode": "  ", "subjectGroupNotes": null, "courseDescription": null, "synopsisUrl": "http://span-port.rutgers.edu/course-synopses", "offeringUnitTitle": null, "openSections": 0, "credits": 3, "offeringUnitCode": "01", "preReqNotes": "(01:940:313 )<em> OR </em>(01:940:325 )<em> OR </em>(01:940:326 )<em> OR </em>(01:940:331 LIT&CULT HISP CARIBB)<em> OR </em>(01:940:331 LIT&CULT HISP CARIBB)<em> OR </em>(01:940:333 )<em> OR </em>(01:940:334 MOD IDENT SPAN AMER)<em> OR </em>(01:940:335 LIT&CULT OF SPAIN)<em> OR </em>(01:940:336 LIT&CULT OF SPAIN)<em> OR </em>(01:940:342 WOM WRTS HISP WORLD)<em> OR </em>(01:940:346 SPANISH FILM)<em> OR </em>(01:940:348 LATIN-AMER CINEMA)<em> OR </em>(01:940:360 )<em> OR </em>(01:940:362 )<em> OR </em>(01:940:363 )<em> OR </em>(01:940:365 RES METH SPAN LING)<em> OR </em>(01:940:366 )<em> OR </em>(01:940:367 SOCIOLNG SPAN SPK WL)", "unitNotes": null, "subjectNotes": "SEE PORTUGUESE(810) FOR ADDITIONAL COURSES. \r\n\r\nFOR ONLINE COURSES SELECT ONLINE COURSES UNDER COURSE TYPE TO SEE COURSE OFFERINGS.", "courseNumber": "403", "expandedTitle": null, "subject": "940"}, {"sections": [{"minors": [], "sessionDates": null, "specialPermissionAddCode": null, "number": "01", "unitMajors": [], "subtitle": null, "specialPermissionDropCodeDescription": null, "specialPermissionAddCodeDescription": null, "subtopic": null, "majors": [], "index": "18762", "sectionNotes": null, "specialPermissionDropCode": null, "comments": [], "crossListedSections": [], "legendKey": null, "meetingTimes": [{"campusName": "COLLEGE AVENUE", "startTime": "0950", "meetingDay": "TH", "meetingModeDesc": "LEC", "roomNumber": "121", "campusLocation": "1", "buildingCode": "SC", "pmCode": "A", "baClassHours": null, "campusAbbrev": "CAC", "endTime": "1110", "meetingModeCode": "02"}, {"campusName": "COLLEGE AVENUE", "startTime": "0950", "meetingDay": "M", "meetingModeDesc": "LEC", "roomNumber": "121", "campusLocation": "1", "buildingCode": "SC", "pmCode": "A", "baClassHours": null, "campusAbbrev": "CAC", "endTime": "1110", "meetingModeCode": "02"}], "honorPrograms": [], "instructors": [{"name": "NUNEZ. O"}], "printed": "Y", "examCode": "C", "campusCode": "NB", "sectionEligibility": null, "sessionDatePrintIndicator": "Y", "openStatus": true}], "campusCode": "NB", "coreCodes": [], "courseNotes": null, "title": "DIALECT SPN-SPK WRLD", "supplementCode": "  ", "subjectGroupNotes": null, "courseDescription": null, "synopsisUrl": "http://span-port.rutgers.edu/course-synopses", "offeringUnitTitle": null, "openSections": 1, "credits": 3, "offeringUnitCode": "01", "preReqNotes": "(01:940:261 )<em> OR </em>(01:940:362 )", "unitNotes": null, "subjectNotes": "SEE PORTUGUESE(810) FOR ADDITIONAL COURSES. \r\n\r\nFOR ONLINE COURSES SELECT ONLINE COURSES UNDER COURSE TYPE TO SEE COURSE OFFERINGS.", "courseNumber": "419", "expandedTitle": null, "subject": "940"}, {"sections": [{"minors": [], "sessionDates": null, "specialPermissionAddCode": null, "number": "01", "unitMajors": [], "subtitle": null, "specialPermissionDropCodeDescription": null, "specialPermissionAddCodeDescription": null, "subtopic": null, "majors": [], "index": "06866", "sectionNotes": null, "specialPermissionDropCode": null, "comments": [{"code": "35", "description": "See online schedule for prereqs"}], "crossListedSections": [{"subjectCode": "940", "supplementCode": "  ", "registrationIndex": "07043", "offeringUnitCode": "16", "primaryRegistrationIndex": "06866", "courseNumber": "575", "offeringUnitCampus": "NB", "sectionNumber": "01"}], "legendKey": null, "meetingTimes": [{"campusName": "COLLEGE AVENUE", "startTime": "0610", "meetingDay": "W", "meetingModeDesc": "LEC", "roomNumber": "5190", "campusLocation": "1", "buildingCode": "AB", "pmCode": "P", "baClassHours": null, "campusAbbrev": "CAC", "endTime": "0730", "meetingModeCode": "02"}, {"campusName": "COLLEGE AVENUE", "startTime": "0610", "meetingDay": "M", "meetingModeDesc": "LEC", "roomNumber": "119", "campusLocation": "1", "buildingCode": "LLB", "pmCode": "P", "baClassHours": null, "campusAbbrev": "CAC", "endTime": "0730", "meetingModeCode": "02"}], "honorPrograms": [], "instructors": [{"name": "JIMENEZ, M"}], "printed": "Y", "examCode": "C", "campusCode": "NB", "sectionEligibility": null, "sessionDatePrintIndicator": "Y", "openStatus": true}], "campusCode": "NB", "coreCodes": [], "courseNotes": null, "title": "INTERPRETING", "supplementCode": "  ", "subjectGroupNotes": null, "courseDescription": null, "synopsisUrl": "http://span-port.rutgers.edu/course-synopses", "offeringUnitTitle": null, "openSections": 1, "credits": 3, "offeringUnitCode": "01", "preReqNotes": "(01:940:401 )<em> OR </em>(01:940:402 )", "unitNotes": null, "subjectNotes": "SEE PORTUGUESE(810) FOR ADDITIONAL COURSES. \r\n\r\nFOR ONLINE COURSES SELECT ONLINE COURSES UNDER COURSE TYPE TO SEE COURSE OFFERINGS.", "courseNumber": "475", "expandedTitle": null, "subject": "940"}, {"sections": [{"minors": [], "sessionDates": null, "specialPermissionAddCode": null, "number": "01", "unitMajors": [], "subtitle": null, "specialPermissionDropCodeDescription": null, "specialPermissionAddCodeDescription": null, "subtopic": null, "majors": [], "index": "18763", "sectionNotes": null, "specialPermissionDropCode": null, "comments": [], "crossListedSections": [{"subjectCode": "940", "supplementCode": "  ", "registrationIndex": "18767", "offeringUnitCode": "16", "primaryRegistrationIndex": "18763", "courseNumber": "563", "offeringUnitCampus": "NB", "sectionNumber": "01"}], "legendKey": null, "meetingTimes": [{"campusName": "COLLEGE AVENUE", "startTime": "0740", "meetingDay": "W", "meetingModeDesc": "LEC", "roomNumber": "5190", "campusLocation": "1", "buildingCode": "AB", "pmCode": "P", "baClassHours": null, "campusAbbrev": "CAC", "endTime": "0900", "meetingModeCode": "02"}, {"campusName": "COLLEGE AVENUE", "startTime": "0740", "meetingDay": "M", "meetingModeDesc": "LEC", "roomNumber": "5190", "campusLocation": "1", "buildingCode": "AB", "pmCode": "P", "baClassHours": null, "campusAbbrev": "CAC", "endTime": "0900", "meetingModeCode": "02"}], "honorPrograms": [], "instructors": [{"name": "JIMENEZ, M"}], "printed": "Y", "examCode": "C", "campusCode": "NB", "sectionEligibility": null, "sessionDatePrintIndicator": "Y", "openStatus": true}], "campusCode": "NB", "coreCodes": [], "courseNotes": null, "title": "THEORY&PRAC TRANSLTN", "supplementCode": "  ", "subjectGroupNotes": null, "courseDescription": null, "synopsisUrl": "http://span-port.rutgers.edu/course-synopses", "offeringUnitTitle": null, "openSections": 1, "credits": 3, "offeringUnitCode": "01", "preReqNotes": "(01:940:401 )<em> AND </em>(01:940:402 )", "unitNotes": null, "subjectNotes": "SEE PORTUGUESE(810) FOR ADDITIONAL COURSES. \r\n\r\nFOR ONLINE COURSES SELECT ONLINE COURSES UNDER COURSE TYPE TO SEE COURSE OFFERINGS.", "courseNumber": "478", "expandedTitle": null, "subject": "940"}, {"sections": [{"minors": [], "sessionDates": null, "specialPermissionAddCode": null, "number": "90", "unitMajors": [], "subtitle": null, "specialPermissionDropCodeDescription": null, "specialPermissionAddCodeDescription": null, "subtopic": null, "majors": [], "index": "18821", "sectionNotes": "\"BILINGUAL LANGUAGE DEVELOPMENTIN CHILDREN\"", "specialPermissionDropCode": null, "comments": [{"code": "56", "description": "Online Course"}, {"code": "61", "description": "$100 Online Course Support fee"}, {"code": "60", "description": "Go to http://Sakai.rutgers.edu"}], "crossListedSections": [{"subjectCode": "940", "supplementCode": "  ", "registrationIndex": "18823", "offeringUnitCode": "16", "primaryRegistrationIndex": "18821", "courseNumber": "588", "offeringUnitCampus": "NB", "sectionNumber": "90"}], "legendKey": null, "meetingTimes": [{"campusName": null, "startTime": null, "meetingDay": null, "meetingModeDesc": "ONLINE INSTRUCTION(INTERNET)", "roomNumber": null, "campusLocation": null, "buildingCode": null, "pmCode": null, "baClassHours": "B", "campusAbbrev": null, "endTime": null, "meetingModeCode": "90"}], "honorPrograms": [], "instructors": [{"name": "LINGWALL, A"}], "printed": "Y", "examCode": "A", "campusCode": "NB", "sectionEligibility": null, "sessionDatePrintIndicator": "Y", "openStatus": true}], "campusCode": "NB", "coreCodes": [], "courseNotes": null, "title": "TOPICS SPAN LING", "supplementCode": "  ", "subjectGroupNotes": null, "courseDescription": null, "synopsisUrl": "http://span-port.rutgers.edu/course-synopses", "offeringUnitTitle": null, "openSections": 1, "credits": 3, "offeringUnitCode": "01", "preReqNotes": "(01:940:261 )", "unitNotes": null, "subjectNotes": "SEE PORTUGUESE(810) FOR ADDITIONAL COURSES. \r\n\r\nFOR ONLINE COURSES SELECT ONLINE COURSES UNDER COURSE TYPE TO SEE COURSE OFFERINGS.", "courseNumber": "488", "expandedTitle": "TOPICS IN SPANISH LINGUISTICS                                                   ", "subject": "940"}, {"sections": [{"minors": [], "sessionDates": null, "specialPermissionAddCode": null, "number": "01", "unitMajors": [], "subtitle": null, "specialPermissionDropCodeDescription": null, "specialPermissionAddCodeDescription": null, "subtopic": null, "majors": [], "index": "18822", "sectionNotes": "\"VIOLENCIA Y CRUELDAD ENLITERATURA CENTROAMERICANA\"", "specialPermissionDropCode": null, "comments": [], "crossListedSections": [], "legendKey": null, "meetingTimes": [{"campusName": "DOUGLAS/COOK", "startTime": "0355", "meetingDay": "TH", "meetingModeDesc": "LEC", "roomNumber": "112", "campusLocation": "4", "buildingCode": "HCK", "pmCode": "P", "baClassHours": null, "campusAbbrev": "D/C", "endTime": "0655", "meetingModeCode": "02"}], "honorPrograms": [], "instructors": [{"name": "NARVAEZ, C"}], "printed": "Y", "examCode": "C", "campusCode": "NB", "sectionEligibility": null, "sessionDatePrintIndicator": "Y", "openStatus": true}], "campusCode": "NB", "coreCodes": [], "courseNotes": null, "title": "TPCS HISP LIT & CULT", "supplementCode": "  ", "subjectGroupNotes": null, "courseDescription": null, "synopsisUrl": "http://span-port.rutgers.edu/course-synopses", "offeringUnitTitle": null, "openSections": 1, "credits": 3, "offeringUnitCode": "01", "preReqNotes": "(01:940:331 LIT&CULT HISP CARIBB)<em> OR </em>(01:940:332 LIT&CULT HISP CARIBB)<em> OR </em>(01:940:333 )<em> OR </em>(01:940:334 MOD IDENT SPAN AMER)<em> OR </em>(01:940:335 LIT&CULT OF SPAIN)<em> OR </em>(01:940:336 LIT&CULT OF SPAIN)<em> OR </em>(01:940:342 WOM WRTS HISP WORLD)", "unitNotes": null, "subjectNotes": "SEE PORTUGUESE(810) FOR ADDITIONAL COURSES. \r\n\r\nFOR ONLINE COURSES SELECT ONLINE COURSES UNDER COURSE TYPE TO SEE COURSE OFFERINGS.", "courseNumber": "491", "expandedTitle": "TOPICS IN HISPANIC LITERATURE AND CULTURE                                       ", "subject": "940"}, {"sections": [{"minors": [], "sessionDates": null, "specialPermissionAddCode": "03", "number": "01", "unitMajors": [], "subtitle": null, "specialPermissionDropCodeDescription": null, "specialPermissionAddCodeDescription": "Department staff", "subtopic": null, "majors": [], "index": "02768", "sectionNotes": "PERMISSION OF DEPARTMENTPREREQ:  ONE TERM OF 400-LEVELSPANISH", "specialPermissionDropCode": null, "comments": [], "crossListedSections": [], "legendKey": null, "meetingTimes": [{"campusName": null, "startTime": null, "meetingDay": null, "meetingModeDesc": "PROJ-IND", "roomNumber": null, "campusLocation": null, "buildingCode": null, "pmCode": null, "baClassHours": "B", "campusAbbrev": null, "endTime": null, "meetingModeCode": "19"}], "honorPrograms": [], "instructors": [], "printed": "Y", "examCode": "A", "campusCode": "NB", "sectionEligibility": null, "sessionDatePrintIndicator": "Y", "openStatus": true}], "campusCode": "NB", "coreCodes": [], "courseNotes": null, "title": "INDEPENDENT STUDY", "supplementCode": "  ", "subjectGroupNotes": null, "courseDescription": null, "synopsisUrl": "http://span-port.rutgers.edu/course-synopses", "offeringUnitTitle": null, "openSections": 1, "credits": null, "offeringUnitCode": "01", "preReqNotes": null, "unitNotes": null, "subjectNotes": "SEE PORTUGUESE(810) FOR ADDITIONAL COURSES. \r\n\r\nFOR ONLINE COURSES SELECT ONLINE COURSES UNDER COURSE TYPE TO SEE COURSE OFFERINGS.", "courseNumber": "493", "expandedTitle": null, "subject": "940"}, {"sections": [{"minors": [], "sessionDates": null, "specialPermissionAddCode": "03", "number": "H1", "unitMajors": [], "subtitle": null, "specialPermissionDropCodeDescription": null, "specialPermissionAddCodeDescription": "Department staff", "subtopic": null, "majors": [], "index": "00458", "sectionNotes": "PERMISSION OF DEPARTMENT", "specialPermissionDropCode": null, "comments": [{"code": "87", "description": "For Honors Students only"}], "crossListedSections": [], "legendKey": null, "meetingTimes": [{"campusName": null, "startTime": null, "meetingDay": null, "meetingModeDesc": "HONORS", "roomNumber": null, "campusLocation": null, "buildingCode": null, "pmCode": null, "baClassHours": "B", "campusAbbrev": null, "endTime": null, "meetingModeCode": "21"}], "honorPrograms": [], "instructors": [], "printed": "Y", "examCode": "A", "campusCode": "NB", "sectionEligibility": null, "sessionDatePrintIndicator": "Y", "openStatus": true}], "campusCode": "NB", "coreCodes": [], "courseNotes": null, "title": "HONORS IN SPANISH", "supplementCode": "  ", "subjectGroupNotes": null, "courseDescription": null, "synopsisUrl": "http://span-port.rutgers.edu/course-synopses", "offeringUnitTitle": null, "openSections": 1, "credits": null, "offeringUnitCode": "01", "preReqNotes": null, "unitNotes": null, "subjectNotes": "SEE PORTUGUESE(810) FOR ADDITIONAL COURSES. \r\n\r\nFOR ONLINE COURSES SELECT ONLINE COURSES UNDER COURSE TYPE TO SEE COURSE OFFERINGS.", "courseNumber": "497", "expandedTitle": null, "subject": "940"}, {"sections": [{"minors": [], "sessionDates": null, "specialPermissionAddCode": null, "number": "90", "unitMajors": [], "subtitle": null, "specialPermissionDropCodeDescription": null, "specialPermissionAddCodeDescription": null, "subtopic": null, "majors": [], "index": "15375", "sectionNotes": "MEETS 10/19-12/13.PREREQ:  940:388 OR 940:389.", "specialPermissionDropCode": null, "comments": [{"code": "13", "description": "Second 7 weeks"}, {"code": "62", "description": "$60 Online Course Support fee"}, {"code": "60", "description": "Go to http://Sakai.rutgers.edu"}, {"code": "56", "description": "Online Course"}], "crossListedSections": [], "legendKey": null, "meetingTimes": [{"campusName": null, "startTime": null, "meetingDay": null, "meetingModeDesc": "ONLINE INSTRUCTION(INTERNET)", "roomNumber": null, "campusLocation": null, "buildingCode": null, "pmCode": null, "baClassHours": "B", "campusAbbrev": null, "endTime": null, "meetingModeCode": "90"}], "honorPrograms": [], "instructors": [{"name": "VILLALBA, C"}], "printed": "Y", "examCode": "A", "campusCode": "NB", "sectionEligibility": "JUNIORS AND SENIORS ", "sessionDatePrintIndicator": "Y", "openStatus": true}], "campusCode": "NB", "coreCodes": [], "courseNotes": null, "title": "ORAL PROFIENCY INTER", "supplementCode": "  ", "subjectGroupNotes": null, "courseDescription": null, "synopsisUrl": "http://span-port.rutgers.edu/course-synopses", "offeringUnitTitle": null, "openSections": 1, "credits": 1, "offeringUnitCode": "01", "preReqNotes": "(01:940:388 SPAN LAB ORAL PROFIC)<em> OR </em>(01:940:389 )", "unitNotes": null, "subjectNotes": "SEE PORTUGUESE(810) FOR ADDITIONAL COURSES. \r\n\r\nFOR ONLINE COURSES SELECT ONLINE COURSES UNDER COURSE TYPE TO SEE COURSE OFFERINGS.", "courseNumber": "499", "expandedTitle": "ORAL PROFICIENCY INTERVIEW                                                      ", "subject": "940"}]